{
  "filename": "Screenshot_20251024-084456 (1).webp",
  "tags": [
    "screenshot",
    "mobile",
    "google",
    "search",
    "profile",
    "writer",
    "student",
    "law",
    "actor",
    "motivational-speaker",
    "instagram",
    "imdb",
    "knowlepedia",
    "social-media",
    "biography"
  ],
  "raw_text": "8:44\n0.00 KB/S\nVOLTE 5G+ 92\nà°¤à±†à°²à±à°—à±à°²à±‹ à°¶à±‹à°§à°¿à°‚à°šà°‚à°¡à°¿\nà°—à±Œà°°à°µà± à°¸à°¿à°‚à°—à± à°šà±Œà°¹à°¾à°¨à±\nGaurav Singh Chouhan\nWriter\nGaurav Singh Chouhan is an aspiring Ba LLB student, content writer, and motivational speaker, with a strong commitment to building a successful career in law. Hailing from the Rajput community, he is recognized for his creativity, writing skills, and passion for inspiring others. ...\nSource: Google Books\nIMDb\nGaurav Singh Chouhan - IMDb\nGaurav Singh Chouhan is an Indian actor, writer, and...\nInstagram\nGaurav Singh Chauhan (@gauravsinghchauhan376 )\nIn As Gaurav |_ - Wanderlust ğŸ˜- ã€Gym Addictã€‘ ğŸ’ª \\_Karma Believer_\\ |Tere Yaar Daa Naam Bahut Hai ğŸ˜ FB ğŸ‘‡ mobile.facebook.com/gauravs...\nIMDb\nhttps://m.imdb.com\nGaurav Singh Chouhan\nGaurav Singh Chouhan is an Indian actor, writer, and motivational speaker. He was born in Delhi, and his family belongs to the Chauhan community from Mainpuri, ...\nKnowlepedia\nhttps://knowlepedia.org\nGaurav Singh Chouhan â€“ Public Figure, Motivational Speaker & Writer ...\n24 Sept 2025 â€” Gaurav Singh Chouhan is an Indian public figure, writer, and motivational speaker. Born in Delhi with family roots in Mainpuri, Uttar Pradesh, ...",
  "structured_data": {
    "profile_summary": {
      "name": "Gaurav Singh Chouhan",
      "professions": [
        "Writer",
        "Aspiring Ba LLB student",
        "Content writer",
        "Motivational speaker",
        "Indian actor",
        "Public figure"
      ],
      "background": {
        "community": "Rajput / Chauhan community",
        "birthplace": "Delhi",
        "roots": "Mainpuri, Uttar Pradesh"
      }
    },
    "social_media_profiles": [
      {
        "platform": "Instagram",
        "name": "Gaurav Singh Chauhan",
        "username": "gauravsinghchauhan376",
        "bio": "In As Gaurav |_ - Wanderlust ğŸ˜- ã€Gym Addictã€‘ ğŸ’ª \\_Karma Believer_\\ |Tere Yaar Daa Naam Bahut Hai ğŸ˜ FB ğŸ‘‡"
      },
      {
        "platform": "IMDb",
        "title": "Gaurav Singh Chouhan - IMDb",
        "url": "https://m.imdb.com"
      },
      {
        "platform": "Knowlepedia",
        "title": "Gaurav Singh Chouhan â€“ Public Figure, Motivational Speaker & Writer ...",
        "url": "https://knowlepedia.org"
      }
    ]
  },
  "profile_mentions": [
    "@gauravsinghchauhan376"
  ],
  "additional_metadata": {
    "urls": [
      "mobile.facebook.com/gauravs...",
      "https://m.imdb.com",
      "https://knowlepedia.org"
    ],
    "dates": [
      "24 Sept 2025"
    ],
    "languages_visible": [
      "English",
      "Telugu"
    ]
  }
}