{
  "filename": "Screenshot_20251012-020541 (1).webp",
  "tags": [
    "screenshot",
    "instagram",
    "profile",
    "smartphone",
    "AI",
    "technology",
    "education",
    "business",
    "marketing",
    "socialmedia",
    "man",
    "video",
    "reels",
    "prompts",
    "chatgpt"
  ],
  "raw_text": "2:05\n1.18 KB/S\nVoLTE\n4G\n61\nsanganisahil.ai\nSahil Sangani\n96 posts\n14.2K followers\n12 following\nHelping you implement AI using AI Education.\nTurn chatgpt into your employee using CustomGPTs.\nJoin my free community for AI Prompts \nwww.skool.com/ai-social-media-system-3585/about?ref=78...\nsanganisahil.ai\nKrishna from Bhagwad Gita 2 more\nFollowed by ai_sign_memes\nFollow\nMessage\nContact\nAI CREATIVE\nYT\nAI app\nAI prompts\nAI Creative Studio\nHello sir.\ntoday I purchase your 999 product\nshoot bundol its very good and very\nosm\nhat are you waiting for? If you\nto buy it, reply back to\n'AI' & let me...\nMAKING MONEY\nWHY YOU'RE\nNew video out!\nAutomation all the way!\nStay tuned for something\nspecial for you guys!\nTHIS AI PROM\nCAN GET YOU\nCLIENTS\nEveryday we try to\nsolve 1 problem using\nAI\nwill be bu...\nOne AI hack you can\nimplement right away.\nSahil Sangani\n@sanganisahil\nOpenAI is launching Sora 2, Sora 2\nPro and Sora app in US and Canada!\n10:58 PM 路 Sep 30, 2025\nEasiest attraction for any tourist spot in India to\nincrease tourism overnight.\nJason Smith - 涓瀹版 @Shangg... 路 9h\n Okay. Now China is just showing off.\nGuizhou Huajiang Canyon Bridge is ALSO the\ntallest man-made WATERFALL in the world at\n625 meters.\nSahil Sangani\n@sanganisahil.ai\nAI Prompt of the\nDay:\nStudy my chat\nhistory & tell me\n1:59 PM 路 Sep 24, 2025\nLearn more\nGo to website",
  "structured_data": {
    "profile": {
      "name": "Sahil Sangani",
      "username": "sanganisahil.ai",
      "is_verified": true,
      "post_count": "96",
      "follower_count": "14.2K",
      "following_count": "12",
      "bio": "Helping you implement AI using AI Education. Turn chatgpt into your employee using CustomGPTs. Join my free community for AI Prompts ",
      "external_links": [
        "www.skool.com/ai-social-media-system-3585/about?ref=78...",
        "sanganisahil.ai",
        "Krishna from Bhagwad Gita"
      ],
      "followed_by": [
        "ai_sign_memes"
      ]
    },
    "highlights": [
      {
        "title": "AI CREATIVE",
        "description": "AI Creative Studio feedback"
      },
      {
        "title": "YT",
        "description": "New video announcements"
      },
      {
        "title": "AI app",
        "description": "Automation updates"
      },
      {
        "title": "AI prompts",
        "description": "Client acquisition prompts"
      }
    ],
    "posts": [
      {
        "type": "Reel",
        "overlay_text": "One AI hack you can implement right away."
      },
      {
        "type": "Reel",
        "author": "@sanganisahil",
        "content": "OpenAI is launching Sora 2, Sora 2 Pro and Sora app in US and Canada!",
        "timestamp": "10:58 PM 路 Sep 30, 2025"
      },
      {
        "type": "Reel",
        "content": "Easiest attraction for any tourist spot in India to increase tourism overnight.",
        "reposted_from": "@Shangg...",
        "repost_content": "Guizhou Huajiang Canyon Bridge is ALSO the tallest man-made WATERFALL in the world at 625 meters."
      },
      {
        "type": "Reel",
        "author": "@sanganisahil.ai",
        "content": "AI Prompt of the Day: Study my chat history & tell me",
        "timestamp": "1:59 PM 路 Sep 24, 2025"
      }
    ]
  },
  "profile_mentions": [
    "@sanganisahil",
    "@Shangg...",
    "@sanganisahil.ai",
    "ai_sign_memes"
  ],
  "additional_metadata": {
    "urls": [
      "www.skool.com/ai-social-media-system-3585/about?ref=78..."
    ],
    "dates": [
      "Sep 30, 2025",
      "Sep 24, 2025"
    ],
    "themes": [
      "AI Education",
      "Custom GPTs",
      "ChatGPT",
      "Sora 2",
      "AI Prompts"
    ]
  }
}