{
  "filename": "Screenshot_20251020-185530 (1).webp",
  "tags": [
    "advertisement",
    "marketing",
    "services",
    "branding",
    "wikipedia",
    "biography",
    "digital_presence",
    "business",
    "promotion",
    "turkish",
    "media"
  ],
  "raw_text": "MarkanÄ±zÄ± Prestijli Platformlarda GÃ¶rÃ¼nÃ¼r KÄ±lÄ±yoruz\nHizmet BaÅŸlÄ±ÄŸÄ±:\nâ€¢ âœ“ Wikipedia baÅŸlangÄ±Ã§ iÃ§erikleri\nâ€¢ âœ“ \"Kimdir?\" biyografi siteleri\nâ€¢ âœ“ Dijital gÃ¶rÃ¼nÃ¼rlÃ¼k ve prestij artÄ±rÄ±cÄ± giriÅŸler\nğŸš€ BaÅŸlangÄ±ca Ã–zel\nğŸ’ª 50 Paketle SÄ±nÄ±rlÄ±\nğŸ’ª %50 Ä°ndirim\nâœ¨ Web'te GÃ¼Ã§lÃ¼ Ä°maj Sizlerle\nSizi dijital dÃ¼nyada gÃ¼Ã§lÃ¼ ve prestijli gÃ¶steriyoruz.\nwww.pyravismedia.com\n10.000 TL (Ã–deme iÅŸ tesliminde)\nwikigenius.org\nEnes KÃ¶seler\nBirth date: April 22, 1996 (age 28)\nBirth place: KadÄ±kÃ¶y, Ä°stanbul, Turkey\nNationality: Turkish\nOccupation: Businessman, Entrepreneur, PR Consultant, TV Producer, Urban Transformation Specialist\nWebsite: eneskoseler.com\nPatronsan\nEnes KÃ¶seler | BaÅŸarÄ± Hikayesi\nMeslek: CEO, Cinsiyet: Erkek, DoÄŸum tarihi: Apr 22, 1996 (29 yaÅŸÄ±nda), DoÄŸum Yeri: Zonguldak\nfounderswiki.org\nEnes KÃ¶seler (born 22 April 1996) is a Turkish entrepreneur and communication professional. He works in the fields of public relations, media production, urban transformation, and marketing. KÃ¶seler is known as the founder of Pyravis Media Production Academy Ltd.\nBiyografya\nEnes KÃ¶seler: Yazar, Ä°letiÅŸimci, ReklamcÄ±, Kent Bilimci\nDoÄŸum: 22 Nisan 1996 Ä°stanbul\nEÄŸitim: YakÄ±n DoÄŸu Ãœniversitesi AB Ä°liÅŸkileri ve Ä°ÅŸletme",
  "structured_data": {
    "service_offer": {
      "headline": "MarkanÄ±zÄ± Prestijli Platformlarda GÃ¶rÃ¼nÃ¼r KÄ±lÄ±yoruz",
      "services": [
        "Wikipedia baÅŸlangÄ±Ã§ iÃ§erikleri",
        "\"Kimdir?\" biyografi siteleri",
        "Dijital gÃ¶rÃ¼nÃ¼rlÃ¼k ve prestij artÄ±rÄ±cÄ± giriÅŸler"
      ],
      "promotion_details": {
        "price": "10.000 TL",
        "payment_condition": "Ã–deme iÅŸ tesliminde",
        "limit": "50 Paketle SÄ±nÄ±rlÄ±",
        "discount": "%50 Ä°ndirim"
      },
      "company": "Pyravis Media",
      "website": "www.pyravismedia.com"
    },
    "example_case_study": {
      "name": "Enes KÃ¶seler",
      "birth_date": "April 22, 1996",
      "nationality": "Turkish",
      "occupations": [
        "Businessman",
        "Entrepreneur",
        "PR Consultant",
        "TV Producer",
        "Urban Transformation Specialist",
        "CEO",
        "Author",
        "Communicator",
        "Advertiser",
        "Urban Scientist"
      ],
      "education": "YakÄ±n DoÄŸu Ãœniversitesi (AB Ä°liÅŸkileri ve Ä°ÅŸletme)",
      "associated_company": "Pyravis Media Production Academy Ltd.",
      "personal_website": "eneskoseler.com"
    }
  },
  "profile_mentions": [],
  "additional_metadata": {
    "urls": [
      "www.pyravismedia.com",
      "wikigenius.org",
      "profil.patronsan.com",
      "founderswiki.org",
      "biyografya.com",
      "eneskoseler.com"
    ],
    "price": "10.000 TL",
    "language": "Turkish",
    "dates": [
      "April 22, 1996"
    ]
  }
}