{
  "filename": "Screenshot_20251015-151502 (1).webp",
  "tags": [
    "screenshot",
    "search",
    "biography",
    "actor",
    "director",
    "cinema",
    "history",
    "India",
    "movies",
    "filmography",
    "IMDb",
    "Instagram",
    "Wikidata"
  ],
  "raw_text": "Charu Roy\nActor\nSource: Alamy\nBorn 6 Sept 1890 Berhampore\nDied 28 Sept 1971 Kolkata\nAbout\nBorn: 6 September 1890, Berhampore\nDied: 28 September 1971 (age 81 years), Kolkata\nPartner: Maya Roy\nMovies\nSHIRAZ\nShiraz 1928\nA Throw of Dice 1929\nBIGRAHA\nBigraha 1930\nKuhu 1936\nIMDb https://m.imdb.com\nCharu Roy(1890-1971)\nCharu Roy was born on 6 September 1890 in Berhampore, Bengal Presidency, British India. He was a director and actor, known for Shiraz (1928), Bigraha (1930) ...\nIMDb https://m.imdb.com\nCharu Shree Roy\nCharu is an Indian film editor who began her career by getting associated with short films as a director and writer. Chasing the Rainbow, a short film, ...\nthecinemawala.com https://thecinemawala.com\nCharu Roy: The Renaissance Man of Indian Cinema - The Cinemawala\n3 May 2025 - Charu Roy wasn't just a filmmaker-he was a cultural chronicler. He was the first editor of India's first cine magazine, Bioscope, and his ...\nWikidata https://www.wikidata.org\nCharu Roy\nCharu Roy, and Seeta Devi in the 1929 film, Prapancha Pasha (A Throw of Dice), directed by Franz Osten.jpg 600 x 280; 36 KB. 1 reference.\nInstagram roycharu 2.2K+ followers\nCharu Shree Roy (@roycharu)\n134 posts 2,239 followers 1,135 following. roycharu. Charu Shree Roy. Student of Cinema... Now & Forever... Editor by profession... storyteller by ...\nBookMyShow https://in.bookmyshow.com\nCharu Roy - Movies, Biography, News, Age & Photos\nCharu Roy (Roy) is a director and actor in the Indian film industry. Roy was born on September 6, 1890 in Berhampore. Roy worked in films like Bangali, Graher ...\nIndiancine.ma https://indiancine.ma\nBangalee (Charu Roy) - Info View\n(1905-59) Actor born in Jessore (now Bangladesh). Degree in literature. Started as a policeman, then Bengali film star from the 20s to the 50s. Began at Madan ...\nRotten Tomatoes https://www.rottentomatoes.com\nCharu Roy Movies List\nExplore the complete filmography of Charu Roy on Rotten Tomatoes! Discover every movie they have been credited in today.",
  "structured_data": {
    "search_subject": "Charu Roy",
    "biographical_details": {
      "born": "6 September 1890, Berhampore",
      "died": "28 September 1971 (age 81 years), Kolkata",
      "partner": "Maya Roy",
      "roles": [
        "Actor",
        "Director",
        "Editor"
      ]
    },
    "movies": [
      {
        "title": "Shiraz",
        "year": "1928"
      },
      {
        "title": "A Throw of Dice",
        "year": "1929"
      },
      {
        "title": "Bigraha",
        "year": "1930"
      },
      {
        "title": "Kuhu",
        "year": "1936"
      }
    ],
    "social_media_profile": {
      "platform": "Instagram",
      "username": "roycharu",
      "name": "Charu Shree Roy",
      "follower_count": "2,239",
      "following_count": "1,135",
      "post_count": "134",
      "bio": "Charu Shree Roy. Student of Cinema... Now & Forever... Editor by profession... storyteller by ..."
    }
  },
  "profile_mentions": [
    "@roycharu"
  ],
  "additional_metadata": {
    "urls": [
      "https://m.imdb.com",
      "https://thecinemawala.com",
      "https://www.wikidata.org",
      "https://in.bookmyshow.com",
      "https://indiancine.ma",
      "https://www.rottentomatoes.com"
    ],
    "dates": [
      "6 Sept 1890",
      "28 Sept 1971",
      "3 May 2025"
    ],
    "locations": [
      "Berhampore",
      "Kolkata",
      "Jessore",
      "Bangladesh"
    ]
  }
}