{
  "filename": "Screenshot_20251102-205114 (1).webp",
  "tags": [
    "screenshot",
    "instagram",
    "smartphone",
    "technology",
    "news",
    "ai",
    "profile",
    "finance",
    "business",
    "robotics",
    "quantum",
    "socialmedia",
    "reels",
    "chatgpt",
    "samaltman",
    "neildegrassetyson",
    "metasmartglasses"
  ],
  "raw_text": "8:51\n328 KB/s VOLTE 5G 31\nuncover.ai\nAI Tools & News | Technology | Artificial Intelligence\n1,113 posts\n494K followers\n10 following\n‚ú® AI to Boost Career, Finance, Business, & Life\n‚ú® Collabs & Marketing: @uncovernews.co\n‚ú® Follow: ü§ñ @uncover.robotics | ‚öõÔ∏è @uncover.quantum\nuncoverai.co/subscribe?utm_source=instagram&utm_mediu...\nuncover.ai\nUncovering AI 9,637 members\nFollowed by john_paulpj and 31 others\nFollow\nMessage\nJust watched\n1.1M\nuncover AI @uncover.ai\nHarvard students show Meta smart glasses can dox anyone in seconds\nuncover AI @uncover.ai\nThe Godfather of AI's chilling warning about his creation\n60 MINUTES\n1.6M\nuncover AI @uncover.ai\nSam Altman the CEO of ChatGPT makes no money\nYou make\nMR. KENNEDY\n2.4M\nCould ChatGPT really replace Google search engine?\nWill ChatGPT\nMR. CRUZ CHAIRMAN\n7,667\nNeil deGrasse Tyson says the earth is flat as he reveals terrifying AI deepfake\nI've been doing\n30.4K\nSam Altman on how GPT-5 can help founders to build startups\nIs there anything that\n89.8K",
  "structured_data": {
    "platform": "Instagram",
    "profile": {
      "username": "uncover.ai",
      "display_name": "AI Tools & News | Technology | Artificial Intelligence",
      "post_count": "1,113",
      "follower_count": "494,000",
      "following_count": "10",
      "bio": "AI to Boost Career, Finance, Business, & Life. Collabs & Marketing: @uncovernews.co. Follow: @uncover.robotics | @uncover.quantum",
      "external_link": "uncoverai.co/subscribe?utm_source=instagram&utm_medium...",
      "broadcast_channel": {
        "name": "Uncovering AI",
        "member_count": "9,637"
      },
      "mutual_followers": "john_paulpj and 31 others"
    },
    "visible_posts": [
      {
        "type": "Reel",
        "title": "Harvard students show Meta smart glasses can dox anyone in seconds",
        "view_count": "1.1M",
        "pinned": true
      },
      {
        "type": "Reel",
        "title": "The Godfather of AI's chilling warning about his creation",
        "view_count": "1.6M",
        "pinned": true
      },
      {
        "type": "Reel",
        "title": "Sam Altman the CEO of ChatGPT makes no money",
        "view_count": "2.4M",
        "pinned": true
      },
      {
        "type": "Reel",
        "title": "Could ChatGPT really replace Google search engine?",
        "view_count": "7,667",
        "pinned": false
      },
      {
        "type": "Reel",
        "title": "Neil deGrasse Tyson says the earth is flat as he reveals terrifying AI deepfake",
        "view_count": "30.4K",
        "pinned": false
      },
      {
        "type": "Reel",
        "title": "Sam Altman on how GPT-5 can help founders to build startups",
        "view_count": "89.8K",
        "pinned": false
      }
    ]
  },
  "profile_mentions": [
    "@uncovernews.co",
    "@uncover.robotics",
    "@uncover.quantum",
    "@john_paulpj",
    "@uncover.ai"
  ],
  "additional_metadata": {
    "url": "https://uncoverai.co/subscribe?utm_source=instagram&utm_medium=...",
    "device_status": {
      "time": "8:51",
      "battery_percentage": "31%",
      "network_type": "5G"
    },
    "notable_people_mentioned": [
      "Sam Altman",
      "Neil deGrasse Tyson",
      "Ted Cruz",
      "John Kennedy",
      "Geoffrey Hinton"
    ],
    "entities_mentioned": [
      "Meta",
      "Harvard",
      "60 Minutes",
      "ChatGPT",
      "Google"
    ]
  }
}