{
  "filename": "Screenshot_20251107-010945 (1).webp",
  "tags": [
    "screenshot",
    "instagram",
    "clothing",
    "retail",
    "sale",
    "shopping",
    "jacket",
    "varsity",
    "fashion",
    "hyderabad",
    "dilsukhnagar",
    "business",
    "advertising"
  ],
  "raw_text": "1:09\n898 KB/s\nVoLTE\n5G\n12\n‚Üê Suggested\nCall : 8985871313\naamir_foodietraveler and baggashub\nFollow\n20.7K\nClothing section - Women Flat 499/- Pick Any item. Kurtis/ tops/jeans etc.\n964\nPremium Mens Clothing Starting From Just 499 Onwards.\nSTORE NAME - BAGGAS HUB\nSTORE LOCATION - PILLAR NO A1555 OPP LIKHITHA DIAGNOSTIC CENTER, DILSUKHNAGAR.\nSTORE CONTACT NUMBER - 8985871313\n147\n34.7K\n#amazon #flipkart #electronics #homeappliance #independancedaysale #clothingsale #surplus #dilsukhnagar\nAugust 7\nFollowed by treedee.exe and 6 others\nüë§ 7 people\nNot interested\nInterested\nSend to chat\nStart a blend",
  "structured_data": {
    "post_info": {
      "platform": "Instagram",
      "authors": [
        "aamir_foodietraveler",
        "baggashub"
      ],
      "caption": "Clothing section - Women Flat 499/- Pick Any item. Kurtis/ tops/jeans etc. Premium Mens Clothing Starting From Just 499 Onwards. STORE NAME - BAGGAS HUB STORE LOCATION - PILLAR NO A1555 OPP LIKHITHA DIAGNOSTIC CENTER, DILSUKHNAGAR. STORE CONTACT NUMBER - 8985871313",
      "likes": "20.7K",
      "comments": "964",
      "reposts": "147",
      "shares": "34.7K",
      "timestamp": "August 7",
      "followed_by": "treedee.exe and 6 others",
      "tagged_count": "7 people"
    },
    "store_details": {
      "name": "BAGGAS HUB",
      "location": "PILLAR NO A1555 OPP LIKHITHA DIAGNOSTIC CENTER, DILSUKHNAGAR",
      "contact_number": "8985871313",
      "pricing_offers": [
        "Women Flat 499/- Pick Any item (Kurtis/ tops/jeans etc.)",
        "Premium Mens Clothing Starting From Just 499 Onwards"
      ]
    }
  },
  "profile_mentions": [
    "aamir_foodietraveler",
    "baggashub",
    "treedee.exe"
  ],
  "additional_metadata": {
    "hashtags": [
      "#amazon",
      "#flipkart",
      "#electronics",
      "#homeappliance",
      "#independancedaysale",
      "#clothingsale",
      "#surplus",
      "#dilsukhnagar"
    ],
    "phone_numbers": [
      "8985871313"
    ],
    "dates": [
      "August 7"
    ],
    "visible_brands": [
      "Burberry"
    ]
  }
}