{
  "filename": "Screenshot_20251008-045947 (1).webp",
  "tags": [
    "advertisement",
    "marketing",
    "infographic",
    "digital-marketing",
    "personal-branding",
    "PR",
    "Wikipedia",
    "biography",
    "Turkish",
    "reputation-management",
    "business",
    "smartphone-screenshot"
  ],
  "raw_text": "MarkanÄ±zÄ± Prestijli Platformlarda GÃ¶rÃ¼nÃ¼r KÄ±lÄ±yoruz\nHizmet BaÅŸlÄ±ÄŸÄ±:\nâ€¢ âœ“ Wikipedia baÅŸlangÄ±Ã§ iÃ§erikleri\nâ€¢ âœ“ \"Kimdir?\" biyografi siteleri\nâ€¢ âœ“ Dijital gÃ¶rÃ¼nÃ¼rlÃ¼k ve prestij artÄ±rÄ±cÄ± giriÅŸler\nğŸš€ BaÅŸlangÄ±ca Ã–zel\nğŸ¥ 50 Paketle SÄ±nÄ±rlÄ±\nğŸ¥ %50 Ä°ndirim\nâœ¨ Webâ€™te GÃ¼Ã§lÃ¼ Ä°maj Sizlerle\nSizi dijital dÃ¼nyada gÃ¼Ã§lÃ¼ ve prestijli gÃ¶steriyoruz.\n10.000 TL (Ã–deme iÅŸ tesliminde)\n03:32 â—„ WA Business wikigenius.org\nof the university youth magazine KampÃ¼ste Anonim.\nEnes KÃ¶seler\nBirth date April 22, 1996 (age 29)\nBirth place KadÄ±kÃ¶y, Ä°stanbul, Turkey\nNationality Turkish\nOccupation Businessman, Entrepreneur, PR Consultant, TV Producer, Urban Transformation Specialist\nWebsite eneskoseler.com\nEarly life and education\nCareer\nPublications\n03:32 â—„ WA Business profil.patronsan.com\nPatronsan Q =\nMeslek CEO\nCinsiyet Erkek\nDoÄŸum tarihi Apr 22, 1996 (29 yaÅŸÄ±nda)\nDoÄŸum Yeri Zonguldak\nPaylaÅŸ\nEnes KÃ¶seler\nBaÅŸarÄ± Hikayesi\nEnes KÃ¶seler - Ä°letiÅŸim Stratejisti, Kentsel DÃ¶nÃ¼ÅŸÃ¼m DanÄ±ÅŸmanÄ±, PR UzmanÄ±, TV YapÄ±mcÄ±sÄ± ve Yazar 1996 yÄ±lÄ±nda Ä°stanbul KadÄ±kÃ¶y'de dÃ¼nyaya gelen Enes KÃ¶seler, medya, iletiÅŸim, pazarlama ve kentsel dÃ¶nÃ¼ÅŸÃ¼m sektÃ¶rlerinde uzmanlaÅŸarak kariyerini Ã§ok yÃ¶nlÃ¼ bir baÅŸarÄ± hikayesine dÃ¶nÃ¼ÅŸtÃ¼rmÃ¼ÅŸtÃ¼r. YakÄ±n DoÄŸu Ãœniversitesi'nde Avrupa BirliÄŸi Ä°liÅŸkileri ve Ä°ÅŸletme eÄŸitimi alan KÃ¶seler, daha sonra Sakarya Ãœniversitesi Edebiyat FakÃ¼ltesi'nde Ã¶ÄŸrenimini sÃ¼rdÃ¼rerek iletiÅŸim ve sosyal bilimler\nDaha fazla gÃ¶ster\n03:31 â—„ WA Business founderswiki.org\nEnes KÃ¶seler\nPage Discussion Tools\nEnes KÃ¶seler (born 22 April 1996) is a Turkish entrepreneur and communication professional. He works in the fields of public relations, media production, urban transformation, and marketing. KÃ¶seler is known as the founder of Pyravis Media Production Academy Ltd., a company active in media education and PR services.\nEnes KÃ¶seler\nBirth date April 22, 1996 (age 29)\nBirth place KadÄ±kÃ¶y, Ä°stanbul, Turkey\nNationality Turkish\nCookies help us deliver our services. By using our services, you agree to our use of cookies. More information OK\n03:32 â—„ WA Business biyografya.com/tr/biographies/enes-koseler...\nBiyografya\nEnes KÃ¶seler\nYazar Ä°letiÅŸimci ReklamcÄ± Kent Bilimci\nDoÄŸum 22 Nisan 1996 Ä°stanbul\nEÄŸitim YakÄ±n DoÄŸu Ãœniversitesi AB Ä°liÅŸkileri ve Ä°ÅŸletme",
  "structured_data": {
    "service_offer": {
      "headline": "MarkanÄ±zÄ± Prestijli Platformlarda GÃ¶rÃ¼nÃ¼r KÄ±lÄ±yoruz",
      "services": [
        "Wikipedia baÅŸlangÄ±Ã§ iÃ§erikleri",
        "\"Kimdir?\" biyografi siteleri",
        "Dijital gÃ¶rÃ¼nÃ¼rlÃ¼k ve prestij artÄ±rÄ±cÄ± giriÅŸler"
      ],
      "promotions": [
        "BaÅŸlangÄ±ca Ã–zel",
        "50 Paketle SÄ±nÄ±rlÄ±",
        "50% Ä°ndirim",
        "Web'te GÃ¼Ã§lÃ¼ Ä°maj"
      ],
      "price": "10.000 TL",
      "payment_terms": "Ã–deme iÅŸ tesliminde (Payment on delivery)"
    },
    "subject_profile": {
      "name": "Enes KÃ¶seler",
      "birth_date": "April 22, 1996",
      "age": "29",
      "birth_place": "KadÄ±kÃ¶y, Ä°stanbul, Turkey (also mentions Zonguldak in one source)",
      "nationality": "Turkish",
      "occupations": [
        "Businessman",
        "Entrepreneur",
        "PR Consultant",
        "TV Producer",
        "Urban Transformation Specialist",
        "CEO",
        "Ä°letiÅŸim Stratejisti",
        "Yazar",
        "Kent Bilimci"
      ],
      "education": [
        "YakÄ±n DoÄŸu Ãœniversitesi (Avrupa BirliÄŸi Ä°liÅŸkileri ve Ä°ÅŸletme)",
        "Sakarya Ãœniversitesi (Edebiyat FakÃ¼ltesi)"
      ],
      "website": "eneskoseler.com"
    }
  },
  "profile_mentions": [],
  "additional_metadata": {
    "urls": [
      "wikigenius.org",
      "profil.patronsan.com",
      "founderswiki.org",
      "biyografya.com",
      "eneskoseler.com"
    ],
    "keywords": [
      "Wikipedia",
      "Kimdir",
      "Prestij",
      "Dijital GÃ¶rÃ¼nÃ¼rlÃ¼k"
    ],
    "company_mention": "Pyravis Media Production Academy Ltd."
  }
}