{
  "filename": "Screenshot_20251021-011335 (1).webp",
  "tags": [
    "screenshot",
    "instagram",
    "smartphone",
    "sustainability",
    "environment",
    "technology",
    "innovation",
    "farming",
    "robotics",
    "renewable-energy",
    "wind-turbine",
    "drone",
    "agriculture"
  ],
  "raw_text": "1:13\n130 KB/S\nVoLTE\n5G\n29\nnopolluting\nNopolluting\n720 posts\n206K followers\n90 following\nNews & media website\nBlending strategy and storytelling to build sustainability.\nTap the link below to feature your business.\nlinktr.ee/nopolluting\nFollowed by goinggreenmedia\nFollow\nMessage\nWhatsApp\n#Nopolluting\nFacts\nGreen resolution\nQuote\nSmart Farming Drones Growing Our Food\nNO POLLUTING\n8,736\nThis City Is Running On 100% Renewable Energy\nNO POLLUTING\n9,636\nWind Turbine That Harness Wind From Any Direction\nNO POLLUTING\n18.3K\nAGROBOT\nGiant Robot With Smart Arms To Handpick Fruits\nThe World's Toughest Wind Turbine\nDog Robot Helping Farmers Around The World\nBoston Dynamics\nmtc",
  "structured_data": {
    "profile": {
      "username": "nopolluting",
      "name": "Nopolluting",
      "category": "News & media website",
      "post_count": "720",
      "follower_count": "206K",
      "following_count": "90",
      "bio": "Blending strategy and storytelling to build sustainability. Tap the link below to feature your business.",
      "external_link": "linktr.ee/nopolluting",
      "followed_by": [
        "goinggreenmedia"
      ]
    },
    "highlights": [
      "#Nopolluting",
      "Facts",
      "Green resolution",
      "Quote"
    ],
    "reels": [
      {
        "title": "Smart Farming Drones Growing Our Food",
        "view_count": "8,736"
      },
      {
        "title": "This City Is Running On 100% Renewable Energy",
        "view_count": "9,636"
      },
      {
        "title": "Wind Turbine That Harness Wind From Any Direction",
        "view_count": "18.3K"
      },
      {
        "title": "Giant Robot With Smart Arms To Handpick Fruits",
        "visible_brand": "AGROBOT"
      },
      {
        "title": "The World's Toughest Wind Turbine"
      },
      {
        "title": "Dog Robot Helping Farmers Around The World",
        "visible_brand": "Boston Dynamics"
      }
    ]
  },
  "profile_mentions": [
    "goinggreenmedia"
  ],
  "additional_metadata": {
    "urls": [
      "linktr.ee/nopolluting"
    ],
    "hashtags": [
      "#Nopolluting"
    ],
    "status_bar": {
      "time": "1:13",
      "network": "5G VoLTE",
      "battery": "29%"
    }
  }
}