{
  "filename": "Screenshot_20251104-193747 (1).webp",
  "tags": [
    "document",
    "text",
    "marketing",
    "campaign",
    "influencer",
    "socialmedia",
    "youtube",
    "spiritual",
    "cultural",
    "motivational",
    "philosophy",
    "DJJS",
    "proposal",
    "strategy"
  ],
  "raw_text": "(b) Influencer-Led Video Campaigns\n• Collaborate with top influencers in the spiritual, cultural and motivational domains (having minimum 1 million+ subscribers/followers and strong engagement) to create and publish 10 videos (12–15 minutes each) on their YouTube and social media channels within a 3-month period.\n• The videos should be hosted by the influencer (speaking on-camera) about Maharaj Ji’s philosophy, DJJS’s social/spiritual contributions and Brahm Gyan.\n• Further, these videos to be published on the influencer’s YouTube/social media channels and cross-posted on DJJS official social platforms\n• Please share List of 15 proposed influencers (with metrics: subscriber/follower count, typical views, engagement rates, geographic reach), with their fees/packages for collaboration.",
  "structured_data": {
    "section_title": "(b) Influencer-Led Video Campaigns",
    "campaign_objectives": [
      {
        "influencer_criteria": "Top influencers in spiritual, cultural, and motivational domains with minimum 1 million+ subscribers/followers and strong engagement",
        "deliverables": "10 videos (12-15 minutes each)",
        "timeline": "3-month period",
        "platforms": [
          "YouTube",
          "Social media channels"
        ]
      },
      {
        "content_focus": [
          "Maharaj Ji’s philosophy",
          "DJJS’s social/spiritual contributions",
          "Brahm Gyan"
        ],
        "format": "Hosted by influencer (speaking on-camera)"
      },
      {
        "distribution_strategy": "Published on influencer’s channels and cross-posted on DJJS official social platforms"
      },
      {
        "action_item": "Provide a list of 15 proposed influencers with specific metrics and fees/packages",
        "required_metrics": [
          "Subscriber/follower count",
          "Typical views",
          "Engagement rates",
          "Geographic reach"
        ]
      }
    ]
  },
  "profile_mentions": [],
  "additional_metadata": {
    "organizations": [
      "DJJS"
    ],
    "key_figures": [
      "Maharaj Ji"
    ],
    "keywords": [
      "Brahm Gyan",
      "Philosophy",
      "Spiritual contributions"
    ]
  }
}