{
  "filename": "Screenshot_20251109-110703 (1).webp",
  "tags": [
    "screenshot",
    "LinkedIn",
    "business",
    "consulting",
    "project",
    "profile",
    "petfood",
    "nutritionist",
    "manufacturing"
  ],
  "raw_text": "Krishnakhi Borgohain â€¢ 2nd\nMasss India | Ex-Analyst Investor Relations at Venture Catalysts\n\nProject details\n\nWhat type of business consulting?\nBusiness plan, New Product / Service / Channel Development\n\nWhat field most closely aligns with your business?\nConsumer Products\n\nIf this is for a business, what is the size of your business?\nIndividual\n\nWhat is the scope of this project?\nOngoing\n\nWhen do you need these services?\nThis week\n\nAny other details about your business consulting needs?\nWe ae looking for a pet food nutrionist who can develop pet food for our manufacturing pet food company. Kindly revert me back.",
  "structured_data": {
    "profile": {
      "name": "Krishnakhi Borgohain",
      "connection_degree": "2nd",
      "current_role": "Masss India",
      "past_experience": "Ex-Analyst Investor Relations at Venture Catalysts"
    },
    "project_details": {
      "type_of_business_consulting": "Business plan, New Product / Service / Channel Development",
      "business_field": "Consumer Products",
      "business_size": "Individual",
      "project_scope": "Ongoing",
      "timeline": "This week",
      "additional_notes": "We ae looking for a pet food nutrionist who can develop pet food for our manufacturing pet food company. Kindly revert me back."
    }
  },
  "profile_mentions": [],
  "additional_metadata": []
}