{
  "filename": "Screenshot_20251028-222109 (1).webp",
  "tags": [
    "screenshot",
    "instagram",
    "profile",
    "furniture",
    "interior_design",
    "business",
    "manufacturing",
    "marketing",
    "social_media",
    "decor",
    "sofa",
    "cabinet"
  ],
  "raw_text": "10:21\nkalsi_furnishings\nKALSI FURNITURE & INTERIOR\nKalsi Furniture and Interior\n34 posts\n5,034 followers\n15 following\nFurniture\nTrusted in Custom & Bulk Furniture Solutionsâœ¨\nManufacturing â€¢ Wholesale â€¢ Custom Furniture\nğŸ“ Kirti Nagar, New Delhi\nğŸ“¦ Order-Based Only\nwww.kalsifurniture.com\nFollow\nMessage\nContact\nComing soon.\nUnveilâœ¨\nTaking shape\nreviews\nReviews\nâœ¨ğŸ‚\nKALSI FURNITURE & INTERIOR\n4. The Cloud Cabinet\n4,420\nKALSI FURNITURE & INTERIOR\nClient: Our carpenter can do this cheaper ğŸ˜’\n15K\nKALSI FURNITURE & INTERIOR\nMade right here. Shook? ğŸ˜¨\n17.3K\nKALSI FURNITURE & INTERIOR\nJust try not to fall in love too fast.. ğŸ¥¹ğŸ¤ğŸ»\nKALSI FURNITURE & INTERIOR\nHere's proof we listen better than your ex. ğŸ‘€â¤ï¸â€ğŸ©¹\nKALSI FURNITURE & INTERIOR\nLook again, bro! ğŸ˜¨",
  "structured_data": {
    "profile_info": {
      "username": "kalsi_furnishings",
      "display_name": "Kalsi Furniture and Interior",
      "category": "Furniture",
      "post_count": 34,
      "follower_count": "5,034",
      "following_count": 15,
      "bio": "Trusted in Custom & Bulk Furniture Solutionsâœ¨ Manufacturing â€¢ Wholesale â€¢ Custom Furniture ğŸ“ Kirti Nagar, New Delhi ğŸ“¦ Order-Based Only",
      "website": "www.kalsifurniture.com",
      "location": "Kirti Nagar, New Delhi"
    },
    "highlights": [
      {
        "title": "Unveilâœ¨",
        "label": "Coming soon."
      },
      {
        "title": "Taking shape",
        "label": "Taking shape"
      },
      {
        "title": "Reviews",
        "label": "reviews"
      },
      {
        "title": "âœ¨ğŸ‚",
        "label": ""
      }
    ],
    "reels_feed": [
      {
        "caption": "4. The Cloud Cabinet",
        "view_count": "4,420"
      },
      {
        "caption": "Client: Our carpenter can do this cheaper ğŸ˜’",
        "view_count": "15K"
      },
      {
        "caption": "Made right here. Shook? ğŸ˜¨",
        "view_count": "17.3K"
      },
      {
        "caption": "Just try not to fall in love too fast.. ğŸ¥¹ğŸ¤ğŸ»"
      },
      {
        "caption": "Here's proof we listen better than your ex. ğŸ‘€â¤ï¸â€ğŸ©¹"
      },
      {
        "caption": "Look again, bro! ğŸ˜¨"
      }
    ]
  },
  "profile_mentions": [],
  "additional_metadata": {
    "url": "www.kalsifurniture.com",
    "business_address": "Kirti Nagar, New Delhi",
    "content_themes": [
      "Custom Furniture",
      "Wholesale Furniture",
      "Order-Based manufacturing"
    ]
  }
}