{
  "filename": "Screenshot_20251102-104635 (1).webp",
  "tags": [
    "recruitment",
    "career",
    "job",
    "pharmaceutical",
    "interview",
    "hiring",
    "ahmedabad",
    "vapi",
    "zydus",
    "pharma",
    "medical",
    "production",
    "quality_control",
    "quality_assurance"
  ],
  "raw_text": "WALK-IN INTERVIEW\nFOR ZYDUS LIFESCIENCES LIMITED\nWe are recruiting for our Topical Ointment plant (Non-Sterile Formulation), Ahmedabad\nProduction\nOfficer / Executive\nQualification : B.Pharm / M.Pharm / B.Tech\nExperience : 3 to 8 Years\nFilling & Packing\nOfficer / Executive\nQualification : B.Pharm / M.Pharm / B.Tech\nExperience : 3 to 8 Years\nPlant Operator / Technical Assistant\nQualification : B.Sc / Diploma / ITI\nExperience : 2 to 7 Years\nQuality Control (Analyst)\nStaff - Officer / Executive\nQualification : M.Sc\nExperience : 3 to 7 Years\nQuality Assurance (IPQA)\nStaff - Officer / Executive\nQualification : B.Pharm / M.Pharm\nExperience : 2 to 5 Years\nJob location\nAhmedabad\nDate:\n9th November 2025 (Sunday)\nTime:\n9 am to 4 pm\nVenue : Hotel Woodlands, National Highway No. 8, near Desai Auto Mobiles, Balitha, Vapi - 396191\nScan to apply\nzydus\nDedicated To Life",
  "structured_data": {
    "organization": "Zydus Lifesciences Limited",
    "event_type": "Walk-in Interview",
    "department_hiring_for": "Topical Ointment plant (Non-Sterile Formulation), Ahmedabad",
    "job_location": "Ahmedabad",
    "interview_schedule": {
      "date": "9th November 2025 (Sunday)",
      "time": "9 am to 4 pm",
      "venue": "Hotel Woodlands, National Highway No. 8, near Desai Auto Mobiles, Balitha, Vapi - 396191"
    },
    "vacancies": [
      {
        "department": "Production",
        "position": "Officer / Executive",
        "qualification": "B.Pharm / M.Pharm / B.Tech",
        "experience": "3 to 8 Years"
      },
      {
        "department": "Filling & Packing",
        "position": "Officer / Executive",
        "qualification": "B.Pharm / M.Pharm / B.Tech",
        "experience": "3 to 8 Years"
      },
      {
        "department": "Filling & Packing",
        "position": "Plant Operator / Technical Assistant",
        "qualification": "B.Sc / Diploma / ITI",
        "experience": "2 to 7 Years"
      },
      {
        "department": "Quality Control (Analyst)",
        "position": "Staff - Officer / Executive",
        "qualification": "M.Sc",
        "experience": "3 to 7 Years"
      },
      {
        "department": "Quality Assurance (IPQA)",
        "position": "Staff - Officer / Executive",
        "qualification": "B.Pharm / M.Pharm",
        "experience": "2 to 5 Years"
      }
    ]
  },
  "profile_mentions": [],
  "additional_metadata": {
    "dates": [
      "9th November 2025"
    ],
    "pincode": "396191",
    "application_method": "Scan to apply (QR code present)",
    "company_motto": "Dedicated To Life"
  }
}