{
  "filename": "Screenshot_20251104-150331 (1).webp",
  "tags": [
    "screenshot",
    "instagram",
    "sandwich",
    "food",
    "business",
    "cooking",
    "celebration",
    "profile",
    "india"
  ],
  "raw_text": "3:03\n29.8 KB/s\nVoLTE 5G\n63\nav.madhuram.sandwich\nAV. Madhuram Sandwich\n334 posts\n97.3K followers\n492 following\nSandwich Shop\nMost Viral Jumbo Sandwich ЁЯек\nOwner @aayush.girothiya & @vaibhav.girothiya\nManaged by @prabhakar.joshi.official\nЁЯУН Kanch Mandir ЁЯУН Bhawarkua ЁЯУН Sch No 140\nЁЯФЧ maps.app.goo.gl/kousr34BWKtEzfJg8 and 3 more\nav.madhuram.sandwich\nFollow\nMessage\nContact\nOpening sch.140\nInfluencers\nInstagram Family\nTHANK YOU 5000 FOLLOWERS FAMILY\nFebruary\n310K\nAV Madhuram рдкрд░рд┐рд╡рд╛рд░ рдХреА рдУрд░ рд╕реЗ рдЫреЛрдЯреА рджреАрдкрд╛рд╡рд▓реА рдХреА рд╣рд╛рд░реНрджрд┐рдХ рд╢реБрднрдХрд╛рдордирд╛рдПрдВ\n53.1K\n60.4K\nрд╢реНрд░реА рд╕рд┐рджреНрдзрд┐рдХрд╛\nрд╕рднреА рд╕рджрд╕реНрдп рд╕рд╛рде, A.V. Madhuram рдХреА рджреАрд╡рд╛рд▓реА рдЦрд╛рд╕ рдЦреБрд╢рд┐рдпрд╛рдБ рдмрд╛рдЯрдиреЗ рд╕реЗ рдмреЭрддреА рд╣реИ\nMADHURAM SANDWICH",
  "structured_data": {
    "profile": {
      "username": "av.madhuram.sandwich",
      "full_name": "AV. Madhuram Sandwich",
      "category": "Sandwich Shop",
      "post_count": "334",
      "follower_count": "97.3K",
      "following_count": "492",
      "bio": "Most Viral Jumbo Sandwich ЁЯек\nOwner @aayush.girothiya & @vaibhav.girothiya\nManaged by @prabhakar.joshi.official\nЁЯУН Kanch Mandir ЁЯУН Bhawarkua ЁЯУН Sch No 140",
      "website_links": [
        "maps.app.goo.gl/kousr34BWKtEzfJg8",
        "av.madhuram.sandwich"
      ],
      "highlights": [
        "Opening sch.140",
        "Influencers",
        "Instagram Family",
        "February"
      ],
      "reel_view_counts": [
        "310K",
        "53.1K",
        "60.4K"
      ]
    }
  },
  "profile_mentions": [
    "@aayush.girothiya",
    "@vaibhav.girothiya",
    "@prabhakar.joshi.official"
  ],
  "additional_metadata": {
    "urls": [
      "https://maps.app.goo.gl/kousr34BWKtEzfJg8"
    ],
    "locations_mentioned": [
      "Kanch Mandir",
      "Bhawarkua",
      "Sch No 140"
    ],
    "hindi_text": [
      "AV Madhuram рдкрд░рд┐рд╡рд╛рд░ рдХреА рдУрд░ рд╕реЗ рдЫреЛрдЯреА рджреАрдкрд╛рд╡рд▓реА рдХреА рд╣рд╛рд░реНрджрд┐рдХ рд╢реБрднрдХрд╛рдордирд╛рдПрдВ",
      "рд╕рднреА рд╕рджрд╕реНрдп рд╕рд╛рде, A.V. Madhuram рдХреА рджреАрд╡рд╛рд▓реА рдЦрд╛рд╕ рдЦреБрд╢рд┐рдпрд╛рдБ рдмрд╛рдЯрдиреЗ рд╕реЗ рдмреЭрддреА рд╣реИ",
      "рд╢реНрд░реА рд╕рд┐рджреНрдзрд┐рдХрд╛"
    ]
  }
}