{
  "filename": "Screenshot_20251019-115334 (1).webp",
  "tags": [
    "screenshot",
    "instagram",
    "socialmedia",
    "parenting",
    "education",
    "toddlers",
    "earlylearning",
    "activities",
    "profile",
    "mobile",
    "ui"
  ],
  "raw_text": "11:53 120 KB/s VoLTE 5G 89\n← activitiesfortoddler\nDADOSAURUS\n479 posts 116K followers 12 following\nEducation\nA DAD- need I say more??\nhelping #parents in making kids a better person.\ncreated #earlylearning videos that helped more than 4000+ parents\nchat.whatsapp.com/Gl2dNYWPEImEKJpo0RWtAA?mode=e...\nactivitiesfortoddler\nDADOSAURUS Updates\nFollow Message\nPARENTING POL... Activities PDFs ACTIVITIES KIDS STORIES\nYou can teach any words using this trick. शब्दों के साथ इंग्लिश के 464K\n325K\nLet's check if your kid ke Lucky for you 7,681\nHighly Independent High High IQ IQ+EQ Zero High Patience Patience मार कुटाई Zero Independent\nThis sheet is magical!!",
  "structured_data": {
    "profile": {
      "username": "activitiesfortoddler",
      "display_name": "DADOSAURUS",
      "category": "Education",
      "bio": "A DAD- need I say more?? helping #parents in making kids a better person. created #earlylearning videos that helped more than 4000+ parents",
      "stats": {
        "posts": "479",
        "followers": "116K",
        "following": "12"
      },
      "verification_status": "Verified",
      "external_links": [
        "chat.whatsapp.com/Gl2dNYWPEImEKJpo0RWtAA?mode=e..."
      ],
      "other_profiles": {
        "threads": "activitiesfortoddler"
      },
      "broadcast_channels": [
        "DADOSAURUS Updates"
      ],
      "highlights": [
        "PARENTING POL...",
        "Activities PDFs",
        "ACTIVITIES",
        "KIDS STORIES"
      ]
    },
    "posts_preview": [
      {
        "type": "reel",
        "title": "You can teach any words using this trick.",
        "views": "464K",
        "pinned": true
      },
      {
        "type": "reel",
        "views": "325K",
        "pinned": true
      },
      {
        "type": "reel",
        "title": "Let's check if your kid ke Lucky for you",
        "views": "7,681"
      },
      {
        "type": "reel",
        "title": "This sheet is magical!!"
      }
    ]
  },
  "profile_mentions": [],
  "additional_metadata": {
    "hashtags": [
      "#parents",
      "#earlylearning"
    ],
    "urls": [
      "chat.whatsapp.com/Gl2dNYWPEImEKJpo0RWtAA?mode=e..."
    ],
    "phone_status": {
      "time": "11:53",
      "network": "5G",
      "battery": "89%"
    }
  }
}