{
  "filename": "Screenshot_20251113-020952 (1).webp",
  "tags": [
    "screenshot",
    "instagram",
    "reel",
    "movie",
    "cinema",
    "running",
    "marathon",
    "sports",
    "biography",
    "bollywood",
    "inspiration",
    "child",
    "athlete"
  ],
  "raw_text": "2:09\n5.54 KB/s\nVOLTE\n5G\n69\ncinemaoriginalz\ncinemaoriginalz\nDeVotchKa, Mychael Danna\nFollow\nHe was too young to understand what \"limits\" meant - and maybe that's why he broke them.\nBudhia Singh: Born to Run - inspired by the incredible true story of the world's youngest marathon runner. A story of pain, purpose, and passion - of a child who ran not just to win, but to prove that dreams have no age.\nThis isn't just a film - it's a reminder that greatness begins when you refuse to stop.\nðŸŽ¬ Budhia singh born to run\nðŸŽµ The winner is\nTags\n#budhiasinghborntorun #manojbajpayee #tillotamashome #bollywood #explorepage #fyp #movie\nSuggested for you\n312K\n705\n2,783\n24K\nSend to chat\nStart a blend",
  "structured_data": {
    "platform": "Instagram",
    "content_type": "Reel",
    "author": {
      "username": "cinemaoriginalz"
    },
    "audio": "DeVotchKa, Mychael Danna - The winner is",
    "post_engagement": {
      "likes": "312K",
      "comments": "705",
      "reposts_or_saves": "2,783",
      "shares": "24K"
    },
    "caption_text": "He was too young to understand what \"limits\" meant - and maybe that's why he broke them. Budhia Singh: Born to Run - inspired by the incredible true story of the world's youngest marathon runner. A story of pain, purpose, and passion - of a child who ran not just to win, but to prove that dreams have no age. This isn't just a film â€“ it's a reminder that greatness begins when you refuse to stop.",
    "movie_reference": "Budhia Singh: Born to Run"
  },
  "profile_mentions": [],
  "additional_metadata": {
    "hashtags": [
      "#budhiasinghborntorun",
      "#manojbajpayee",
      "#tillotamashome",
      "#bollywood",
      "#explorepage",
      "#fyp",
      "#movie"
    ],
    "status_bar_info": {
      "time": "2:09",
      "data_speed": "5.54 KB/s",
      "network": "5G VOLTE",
      "battery": "69%"
    },
    "suggested_content": "Suggested for you"
  }
}