{
  "filename": "Screenshot_20251018-100131 (1).webp",
  "tags": [
    "advertisement",
    "marketing",
    "services",
    "branding",
    "PR",
    "Wikipedia",
    "Turkey",
    "business",
    "pricing",
    "Turkish",
    "digital",
    "professional",
    "media",
    "identity"
  ],
  "raw_text": "Sizi TanÄ±nan Bir Ä°sim Haline Getiriyoruz\nWikigenius, FoundersWiki ve Biyografya'da dijital kimliÄŸinizi inÅŸa ediyoruz. ÅahsÄ±nÄ±zÄ±n, ÅŸirketinizin, derneÄŸinizin veya projenizin profesyonel profilini, gÃ¼venilir ve prestijli platformlarda oluÅŸturuyoruz.\nâ€¢ Åahsi 3'lÃ¼ Paket\nWikigenius + FoundersWiki + Biyografya profili 10.000 TL\nâ€¢ Åahsi + Åirket Profili\nKiÅŸisel + Kurumsal profil oluÅŸturma 15.000 TL\nâ€¢ Ä°ki Dilli YayÄ±n (TR & EN)\nTÃ¼rkÃ§e ve Ä°ngilizce dilinde yayÄ±n 12.500 TL\nâ€¢ 2 Ulusal Gazetede Haber YayÄ±nÄ± +8.000 TL\nâ€¢ Google Bilgi Paneli Entegrasyonu dahil 25.000 TL\nâ€¢ TÃ¼rkÃ§e & Ä°ngilizce metin hazÄ±rlÄ±ÄŸÄ± +2.000 TL\nâ€¢ 40+ haber sitesinde PR yayÄ±nÄ± +6.000 TL\nEn Ã‡ok Tercih Edilen Paketler;\nÅahsi 3'lÃ¼ Paket + Gazete YayÄ±nÄ±: 17.500 TL\nÅahsi + Åirket Profili + Gazete YayÄ±nÄ±: 18.000 TL\nÅahsi 3'lÃ¼ + Bilgi Paneli: 25.000 TL\nFull PR Paketi (TÃ¼m Hizmetler Dahil): 29.000 TL\nğŸ“ Pyravis Medya YapÄ±m & Akademi YazÄ±lÄ±m Ltd. Åti.\n\"Dijital kimliÄŸinizi profesyonel ÅŸekilde biz inÅŸa ediyoruz.\"\nwww.pyravismedia.com\nSizde globalde yerinizi alÄ±n ğŸ”¥ ğŸ’«\n03:32\nwikigenius.org\nof the university youth magazine KampÃ¼ste Anonim.\nEnes KÃ¶seler\nBirth date April 22, 1996 (age 29)\nBirth place KadÄ±kÃ¶y, Ä°stanbul, Turkey\nNationality Turkish\nOccupation Businessman, Entrepreneur, PR Consultant, TV Producer, Urban Transformation Specialist\nWebsite eneskoseler.com\nEarly life and education\nCareer\nPublications\n03:32\nprofil.patronsan.com\nPatronsan\nMeslek CEO\nCinsiyet Erkek\nDoÄŸum tarihi Apr 22, 1996 (29 yaÅŸÄ±nda)\nDoÄŸum Yeri Zonguldak\nEnes KÃ¶seler\nBaÅŸarÄ± Hikayesi\nEnes KÃ¶seler - Ä°letiÅŸim Stratejisti, Kentsel DÃ¶nÃ¼ÅŸÃ¼m DanÄ±ÅŸmanÄ±, PR UzmanÄ±, TV YapÄ±mcÄ±sÄ± ve Yazar 1996 yÄ±lÄ±nda Ä°stanbul KadÄ±kÃ¶y'de dÃ¼nyaya gelen Enes KÃ¶seler, medya, iletiÅŸim, pazarlama ve kentsel dÃ¶nÃ¼ÅŸÃ¼m sektÃ¶rlerinde uzmanlaÅŸarak kariyerini Ã§ok yÃ¶nlÃ¼ bir baÅŸarÄ± hikayesine dÃ¶nÃ¼ÅŸtÃ¼rmÃ¼ÅŸtÃ¼r. YakÄ±n DoÄŸu Ãœniversitesi'nde Avrupa BirliÄŸi Ä°liÅŸkileri ve Ä°ÅŸletme eÄŸitimi alan KÃ¶seler, daha sonra Sakarya Ãœniversitesi Edebiyat FakÃ¼ltesi'nde Ã¶ÄŸrenimini sÃ¼rdÃ¼rerek iletiÅŸim ve sosyal bilimler\n03:31\nfounderswiki.org\nEnes KÃ¶seler\nEnes KÃ¶seler (born 22 April 1996) is a Turkish entrepreneur and communication professional. He works in the fields of public relations, media production, urban transformation, and marketing. KÃ¶seler is known as the founder of Pyravis Media Production Academy Ltd., a company active in media education and PR services.\nEnes KÃ¶seler\nBirth date April 22, 1996 (age 29)\nBirth place KadÄ±kÃ¶y, Ä°stanbul, Turkey\nNationality Turkish\n03:32\nwww.biyografya.com/biyografies/enes-kos...\nBiyografya\nEnes KÃ¶seler\nYazar Ä°letiÅŸimci ReklamcÄ± Kent Bilimci\nDoÄŸum 22 Nisan 1996 Ä°stanbul\nEÄŸitim YakÄ±n DoÄŸu Ãœniversitesi AB Ä°liÅŸkileri ve Ä°ÅŸletme",
  "structured_data": {
    "service_provider": {
      "company_name": "Pyravis Medya YapÄ±m & Akademi YazÄ±lÄ±m Ltd. Åti.",
      "website": "www.pyravismedia.com",
      "tagline": "Dijital kimliÄŸinizi profesyonel ÅŸekilde biz inÅŸa ediyoruz."
    },
    "pricing_packages": [
      {
        "name": "Åahsi 3'lÃ¼ Paket",
        "description": "Wikigenius + FoundersWiki + Biyografya profili",
        "price": "10.000 TL"
      },
      {
        "name": "Åahsi + Åirket Profili",
        "description": "KiÅŸisel + Kurumsal profil oluÅŸturma",
        "price": "15.000 TL"
      },
      {
        "name": "Ä°ki Dilli YayÄ±n (TR & EN)",
        "description": "TÃ¼rkÃ§e ve Ä°ngilizce dilinde yayÄ±n",
        "price": "12.500 TL"
      },
      {
        "name": "Most Preferred: Åahsi 3'lÃ¼ Paket + Gazete YayÄ±nÄ±",
        "price": "17.500 TL"
      },
      {
        "name": "Most Preferred: Åahsi + Åirket Profili + Gazete YayÄ±nÄ±",
        "price": "18.000 TL"
      },
      {
        "name": "Most Preferred: Åahsi 3'lÃ¼ + Bilgi Paneli",
        "price": "25.000 TL"
      },
      {
        "name": "Full PR Paketi (TÃ¼m Hizmetler Dahil)",
        "price": "29.000 TL"
      }
    ],
    "add_on_services": [
      {
        "name": "2 Ulusal Gazetede Haber YayÄ±nÄ±",
        "price": "+8.000 TL"
      },
      {
        "name": "Google Bilgi Paneli Entegrasyonu",
        "price": "25.000 TL"
      },
      {
        "name": "TÃ¼rkÃ§e & Ä°ngilizce metin hazÄ±rlÄ±ÄŸÄ±",
        "price": "+2.000 TL"
      },
      {
        "name": "40+ haber sitesinde PR yayÄ±nÄ±",
        "price": "+6.000 TL"
      }
    ],
    "example_person_profile": {
      "name": "Enes KÃ¶seler",
      "birth_date": "April 22, 1996",
      "birth_place": "KadÄ±kÃ¶y, Ä°stanbul, Turkey",
      "occupations": [
        "Businessman",
        "Entrepreneur",
        "PR Consultant",
        "TV Producer",
        "Urban Transformation Specialist",
        "CEO"
      ],
      "education": "YakÄ±n DoÄŸu Ãœniversitesi (AB Ä°liÅŸkileri ve Ä°ÅŸletme), Sakarya Ãœniversitesi"
    }
  },
  "profile_mentions": [],
  "additional_metadata": {
    "urls": [
      "www.pyravismedia.com",
      "wikigenius.org",
      "profil.patronsan.com",
      "founderswiki.org",
      "www.biyografya.com",
      "eneskoseler.com"
    ],
    "hashtags": [],
    "languages": [
      "Turkish",
      "English"
    ],
    "emojis": [
      "ğŸ“",
      "ğŸ”¥",
      "ğŸ’«"
    ]
  }
}