{
  "filename": "Screenshot_20251113-052145 (1).webp",
  "tags": [
    "screenshot",
    "instagram",
    "profile",
    "freelancer",
    "video-editing",
    "social-media",
    "entrepreneurship",
    "technology",
    "smartphone",
    "interface",
    "career"
  ],
  "raw_text": "5:21\n0.00 KB/S\nVoLTE 5G 47\nedits_xprince\nPRINCE YADAV | FREELANCER\n76 posts\n22.3K followers\n81 following\nYOUNGEST FREELANCER OF ðŸ‡®ðŸ‡³\n@100x_media\nI help entrepreneurs & creators get 10x reach with viral short-form cont... more\nlinktw.in/grRdVu and 1 more\nedits_xprince\nFollowed by kishore.rabha and ai_sign_memes\nFollow\nMessage\nResults ðŸ“Š\nðŸš€ Assets\nðŸŽ¥ YouTube\n20K\n21.3K\n17.4K\nShe- Why you don't come to school regularly?\nMe- Bcoz I edit videos for top influencers!\n@edits_xprince\nWhen a 14y/o starts cooking for Top influencers instead of studying all day..!\nbhai video editing mai\nDREAMS DON'T WORK UNLESS YOU DO\nTHINK OUTSIDE THE BOX\nwhich software is easy for beginners? Replying to follow karlo\nGoogle Chrome",
  "structured_data": {
    "profile": {
      "name": "PRINCE YADAV | FREELANCER",
      "username": "edits_xprince",
      "posts": 76,
      "followers": "22.3K",
      "following": 81,
      "bio": "YOUNGEST FREELANCER OF ðŸ‡®ðŸ‡³ @100x_media I help entrepreneurs & creators get 10x reach with viral short-form cont...",
      "threads_handle": "edits_xprince",
      "followed_by": [
        "kishore.rabha",
        "ai_sign_memes"
      ]
    },
    "story_highlights": [
      "Results ðŸ“Š",
      "ðŸš€ Assets",
      "ðŸŽ¥ YouTube"
    ],
    "pinned_posts": [
      {
        "text": "She- Why you don't come to school regularly? Me- Bcoz I edit videos for top influencers!",
        "views": "20K"
      },
      {
        "text": "@edits_xprince",
        "views": "21.3K"
      },
      {
        "text": "When a 14y/o starts cooking for Top influencers instead of studying all day..!",
        "views": "17.4K"
      }
    ]
  },
  "profile_mentions": [
    "@100x_media",
    "@edits_xprince"
  ],
  "additional_metadata": {
    "urls": [
      "linktw.in/grRdVu"
    ],
    "phone_status_bar": {
      "time": "5:21",
      "network": "5G",
      "data_speed": "0.00 KB/S",
      "battery_level": "47%"
    }
  }
}