{
  "filename": "Screenshot_20251102-200929 (1).webp",
  "tags": [
    "screenshot",
    "instagram",
    "social_media",
    "environment",
    "sustainability",
    "ngo",
    "waste_management",
    "trees",
    "dustbins",
    "activism",
    "foundation",
    "profile",
    "reels"
  ],
  "raw_text": "8:09 \n277 KB/s VOLTE 5G 37\nswachroots\nSwach Roots\n57 posts\n1,743 followers\n31 following\n\"From waste to Woods\"\nInitiative by @adv.tarun_ and @vishal2129\nEmail - swachhroots@gmail.com\nWaste collected - 4750 kg, Trees planted - 210\nFollowed by theangryindian.in\nFollow\nMessage\nJoin us in this battle even from anywhere! Start from within!\nFROM WASTE TO WOODS\nswachroots\n198K\nSo that Delhites can learn this!\nTypes of Dustbins\nNon-biodegradable Waste\nBiodegradable Waste\nDry & Non-biodegradable Waste\nRight colour dustbins for right waste!\n202K\n@swachroots Foundation\n15.2K\n4,465\nWe are trying to help people identify this!\nJust watched\nBut we alone can't unless you acknowledge!\n37K\nEco Activists destroying painting in the name of awareness and fame!\nStill getting views and headlines!\n8,117\nEvery follower deserves a tree 1 Follow = 1 Tree!\nEvery follower deserves a tree 1 Follow = 1 Tree!",
  "structured_data": {
    "profile_info": {
      "username": "swachroots",
      "display_name": "Swach Roots",
      "post_count": 57,
      "follower_count": 1743,
      "following_count": 31,
      "bio": "\"From waste to Woods\" Initiative by @adv.tarun_ and @vishal2129 Email - swachhroots@gmail.com Waste collected - 4750 kg, Trees planted - 210",
      "followed_by": "theangryindian.in"
    },
    "reels": [
      {
        "caption_snippet": "Join us in this battle even from anywhere! Start from within!",
        "view_count": "198K",
        "is_pinned": true
      },
      {
        "caption_snippet": "So that Delhites can learn this! Types of Dustbins. Right colour dustbins for right waste!",
        "view_count": "202K",
        "is_pinned": true
      },
      {
        "caption_snippet": "@swachroots Foundation",
        "view_count": "15.2K",
        "is_pinned": true
      },
      {
        "view_count": "4,465"
      },
      {
        "caption_snippet": "We are trying to help people identify this! But we alone can't unless you acknowledge!",
        "view_count": "37K"
      },
      {
        "caption_snippet": "Eco Activists destroying painting in the name of awareness and fame! Still getting views and headlines!",
        "view_count": "8,117"
      }
    ]
  },
  "profile_mentions": [
    "@adv.tarun_",
    "@vishal2129",
    "@swachroots"
  ],
  "additional_metadata": {
    "email": "swachhroots@gmail.com",
    "impact_stats": {
      "waste_collected_kg": 4750,
      "trees_planted": 210
    },
    "campaign_slogans": [
      "From waste to Woods",
      "1 Follow = 1 Tree!"
    ]
  }
}