{
  "filename": "Screenshot_20251019-214952 (1).webp",
  "tags": [
    "screenshot",
    "instagram",
    "profile",
    "startup",
    "india",
    "entrepreneurship",
    "business",
    "marketing",
    "funding",
    "education",
    "social-media",
    "app"
  ],
  "raw_text": "9:49 11.8 MB/s VoLTE 5G 40\nindianstartupacademy\nIndian Startup Academy\n147 posts\n28.1K followers\n92 following\nVoice of Indian Startups ðŸ‡®ðŸ‡³\nIdeas | Funding | Ads | Marketing etc.\nEx-Incubation Manager (IIT-Hyderabad)\nSocial Entrepreneur | TISS Tuljapur\nplay.google.com/store/apps/details?id=com.peerup\nindianstartupacademy\nIndian Startups Academy\nFollowing\nMessage\nSuggested for you See all\nindistartuptalks Indi Startup Talks Follow\nstartupchai.in StartupChai Follow\neco... E-co...\nAI STARTUPS AI STARTUPS & INNOVATION\nSTARTUPS FOR... STARTUPS FOR DIFFERENTLY ABLED & INNOVATION\nECO STARTUPS ECO-FRIENDLY STARTUPS & INNOVATION\nHEALTHCARE ST... HEALTHCARE STARTUPS & INNOVATION\nLearn English For Free\nPaper Made House",
  "structured_data": {
    "profile": {
      "name": "Indian Startup Academy",
      "username": "indianstartupacademy",
      "bio": "Voice of Indian Startups ðŸ‡®ðŸ‡³\nIdeas | Funding | Ads | Marketing etc.\nEx-Incubation Manager (IIT-Hyderabad)\nSocial Entrepreneur | TISS Tuljapur",
      "post_count": "147",
      "follower_count": "28.1K",
      "following_count": "92",
      "profile_link": "play.google.com/store/apps/details?id=com.peerup",
      "other_accounts": {
        "threads": "indianstartupacademy",
        "facebook": "Indian Startups Academy"
      }
    },
    "suggested_profiles": [
      {
        "username": "indistartuptalks",
        "name": "Indi Startup Talks"
      },
      {
        "username": "startupchai.in",
        "name": "StartupChai"
      }
    ],
    "story_highlights": [
      "AI STARTUPS & INNOVATION",
      "STARTUPS FOR DIFFERENTLY ABLED & INNOVATION",
      "ECO-FRIENDLY STARTUPS & INNOVATION",
      "HEALTHCARE STARTUPS & INNOVATION"
    ],
    "pinned_posts_previews": [
      "Learn English For Free",
      "Paper Made House"
    ]
  },
  "profile_mentions": [],
  "additional_metadata": {
    "urls": [
      "https://play.google.com/store/apps/details?id=com.peerup"
    ],
    "hashtags": [],
    "status_bar_info": {
      "time": "9:49",
      "data_speed": "11.8 MB/s",
      "network": "VoLTE 5G",
      "battery": "40%"
    }
  }
}