{
  "filename": "Screenshot_20251020-094958 (1).webp",
  "tags": [
    "recipe",
    "maggi",
    "masala",
    "spices",
    "cooking",
    "indian",
    "food",
    "ingredients",
    "handmade",
    "homemade"
  ],
  "raw_text": "Dry red chilli\nЁЯМ╢ Handmade Maggi Masala Recipe (Market Wala Taste)\nAthena Lounge & Bar\nЁЯЫТ Ingredients (Masala Powder ke liye):\n1. Coriander Powder (рдзрдирд┐рдпрд╛ рдкрд╛рдЙрдбрд░) тАУ 2 tsp\n2. Red Chilli Powder (рд▓рд╛рд▓ рдорд┐рд░реНрдЪ рдкрд╛рдЙрдбрд░) тАУ 1 tsp\n3. Turmeric Powder (рд╣рд▓реНрджреА) тАУ ┬╜ tsp\n4. Cumin Powder (рдЬреАрд░рд╛ рдкрд╛рдЙрдбрд░) тАУ ┬╜ tsp\n5. Black Pepper Powder (рдХрд╛рд▓реА рдорд┐рд░реНрдЪ рдкрд╛рдЙрдбрд░) тАУ ┬╜ tsp\n6. Dry Mango Powder (рдЕрдордЪреВрд░) тАУ 1 tsp\n7. Garam Masala тАУ 1 tsp\n8. Kasuri Methi (dry) тАУ 1 tsp (lightly crushed)\n9. Salt (рдирдордХ) тАУ as per taste\n10. Sugar (рдереЛреЬрд╛ рдореАрдард╛рдкрди) тАУ ┬╜ tsp (optional, but gives Maggi jaisa balance)\n11. Onion Powder (рдкреНрдпрд╛реЫ рдкрд╛рдЙрдбрд░) тАУ ┬╜ tsp (optional)\n12. Garlic Powder (рд▓рд╣рд╕реБрди рдкрд╛рдЙрдбрд░) тАУ ┬╜ tsp (optional)",
  "structured_data": {
    "recipe_title": "Handmade Maggi Masala Recipe (Market Wala Taste)",
    "category": "Masala Powder",
    "ingredients": [
      {
        "index": 1,
        "name": "Coriander Powder (рдзрдирд┐рдпрд╛ рдкрд╛рдЙрдбрд░)",
        "quantity": "2 tsp"
      },
      {
        "index": 2,
        "name": "Red Chilli Powder (рд▓рд╛рд▓ рдорд┐рд░реНрдЪ рдкрд╛рдЙрдбрд░)",
        "quantity": "1 tsp"
      },
      {
        "index": 3,
        "name": "Turmeric Powder (рд╣рд▓реНрджреА)",
        "quantity": "┬╜ tsp"
      },
      {
        "index": 4,
        "name": "Cumin Powder (рдЬреАрд░рд╛ рдкрд╛рдЙрдбрд░)",
        "quantity": "┬╜ tsp"
      },
      {
        "index": 5,
        "name": "Black Pepper Powder (рдХрд╛рд▓реА рдорд┐рд░реНрдЪ рдкрд╛рдЙрдбрд░)",
        "quantity": "┬╜ tsp"
      },
      {
        "index": 6,
        "name": "Dry Mango Powder (рдЕрдордЪреВрд░)",
        "quantity": "1 tsp"
      },
      {
        "index": 7,
        "name": "Garam Masala",
        "quantity": "1 tsp"
      },
      {
        "index": 8,
        "name": "Kasuri Methi (dry)",
        "quantity": "1 tsp (lightly crushed)"
      },
      {
        "index": 9,
        "name": "Salt (рдирдордХ)",
        "quantity": "as per taste"
      },
      {
        "index": 10,
        "name": "Sugar (рдереЛреЬрд╛ рдореАрдард╛рдкрди)",
        "quantity": "┬╜ tsp",
        "notes": "optional, but gives Maggi jaisa balance"
      },
      {
        "index": 11,
        "name": "Onion Powder (рдкреНрдпрд╛реЫ рдкрд╛рдЙрдбрд░)",
        "quantity": "┬╜ tsp",
        "notes": "optional"
      },
      {
        "index": 12,
        "name": "Garlic Powder (рд▓рд╣рд╕реБрди рдкрд╛рдЙрдбрд░)",
        "quantity": "┬╜ tsp",
        "notes": "optional"
      }
    ],
    "location_branding": "Athena Lounge & Bar"
  },
  "profile_mentions": [],
  "additional_metadata": {}
}