{
  "filename": "Screenshot_20251103-002714 (1).webp",
  "tags": [
    "screenshot",
    "instagram",
    "profile",
    "entrepreneur",
    "finance",
    "ai",
    "technology",
    "money",
    "lifestyle",
    "dubai",
    "marketing",
    "reels",
    "business",
    "socialmedia"
  ],
  "raw_text": "12:27\nfpsmithh\nFrankie Smith | AI Method\n186 posts\n17.3K followers\n0 following\nEntrepreneur\ni make people money with Ai it's as simple as that\nDm me \"Ai\" to work with me\nFollow\nWins (2)\nAI Method\nDubai ðŸ‡¦ðŸ‡ª\nWins (1)\nIf Sophie rain can make 4 mill in a month with OF...\n(your AI girl can at least make 10k)\n@fpsmithh\nHow is the ðŸ¤– method not illegal ðŸ˜­\nNOW BEFORE I\nUp $6300 today because Jamie from Michigan tipped my AI Girl to go \"shopping\"\n(I keep 100% of the profits ðŸ¤«)\nPOV: you never have to work again thanks to ai girls ðŸ˜®ðŸ’¨\nPOV: You made an ai girl now she pays for your rent in Dubai ðŸ¤«\n(all i had to do was set her up)\nFanvue\nTip Received from Fanvue @stevebrooks Sent you a tip for $25.00\nNew Purchase from Fanvue @stevebrooks Purchased your message for $45.85\nNew Purchase from Fanvue @unaware-constrictor-27 Purchased your message for $53.79\nNew Purchase from Fanvue @unaware-chameleon-62 Purchased your message for $25.97\n2,984\n2,770\n5,672\nTip Received from Fanvue @educational-aardwolf-71 Sent you a tip for $3.47\nNew Purchase from Fanvue @shaky-hookworm-58 Purchased your message for $24.78",
  "structured_data": {
    "profile": {
      "username": "fpsmithh",
      "name": "Frankie Smith | AI Method",
      "post_count": 186,
      "follower_count": "17.3K",
      "following_count": 0,
      "category": "Entrepreneur",
      "bio": "i make people money with Ai it's as simple as that Dm me \"Ai\" to work with me",
      "verification_status": "verified"
    },
    "reels_metrics": [
      {
        "caption": "If Sophie rain can make 4 mill in a month with OF... (your AI girl can at least make 10k)",
        "views": "2,984"
      },
      {
        "caption": "How is the ðŸ¤– method not illegal ðŸ˜­",
        "views": "2,770"
      },
      {
        "caption": "Up $6300 today because Jamie from Michigan tipped my AI Girl to go \"shopping\" (I keep 100% of the profits ðŸ¤«)",
        "views": "5,672"
      }
    ],
    "revenue_notifications": [
      {
        "platform": "Fanvue",
        "type": "Tip",
        "amount": "$25.00",
        "user": "@stevebrooks"
      },
      {
        "platform": "Fanvue",
        "type": "Message Purchase",
        "amount": "$45.85",
        "user": "@stevebrooks"
      },
      {
        "platform": "Fanvue",
        "type": "Message Purchase",
        "amount": "$53.79",
        "user": "@unaware-constrictor-27"
      },
      {
        "platform": "Fanvue",
        "type": "Message Purchase",
        "amount": "$25.97",
        "user": "@unaware-chameleon-62"
      }
    ]
  },
  "profile_mentions": [
    "@fpsmithh",
    "@stevebrooks",
    "@unaware-constrictor-27",
    "@unaware-chameleon-62",
    "@educational-aardwolf-71",
    "@shaky-hookwolf-58"
  ],
  "additional_metadata": {
    "locations_mentioned": [
      "Dubai",
      "Michigan"
    ],
    "platforms_mentioned": [
      "Fanvue",
      "OF (OnlyFans)",
      "Instagram"
    ],
    "time_of_screenshot": "12:27",
    "battery_level": "5%"
  }
}