{
  "filename": "Screenshot_20251102-224250 (1).webp",
  "tags": [
    "screenshot",
    "instagram",
    "profile",
    "marketing",
    "influencer",
    "real-estate",
    "business",
    "digital-marketing",
    "social-media",
    "india",
    "advertising",
    "reels",
    "video",
    "finance"
  ],
  "raw_text": "10:42\nskillsindia.in\nGaurav Kumar Bhushan | Real Estate Digital Marketer\n82 posts 28K followers 600 following\nAdvertising Agency\nüèôÔ∏è Super Specialist Of Real Estate Marketing\nüèÜIcon of Asia Best Marketer for Real estate 2022\nPersuasion Expert\nAthletes Social media manager.\nyoutube.com/@skillsindiain?si=kaUliSLCeqOxTuUc and 1 m...\nskillsindia.in\nThey Think I'm Hiding in the Shadows... b...\nFollow Message Subscribe\nProduct Shoots growth sec 5 - Gurgaon Peak Male Conten\nHey PrabhuüòÇ\nReality of \"Mera Abdul\" | The Hindu-Muslim Brainwash Agenda | Dhruv Rathee\nDhruv Rathee 18.7M\n472K Share Remix Thanks\nComments 73K\n‡§ï‡§≠‡•Ä ‡§¶‡•á‡§ñ‡§æ ‡§π‡•à ‡§™‡•ç‡§∞‡§ß‡§æ‡§®‡§Æ‡§Ç‡§§‡•ç‡§∞‡•Ä ‡§Ü‡§µ‡§æ‡§∏ ‡§Ø‡•ã‡§ú‡§®‡§æ ‡§ï‡§æ ‡§ò‡§∞?\n147K\nThis Is 100% Working Hack to get Viral On Instagram\n248K\nFROM ZERO TO ‚Çπ 5 LAKH IN COFFEE SALES?\nIT'S NOT A DREAM! I'LL SHOW YOU HOW\n500K VIEWS\n565K\nAI Overview\nIt takes a huge amount of water to grow one grain of rice, but the exact amount is difficult to calculate due to high variability in water usage and the grain's small size. On aver... about 5,600 lit...\nis Crazy‚ö†Ô∏èüí•",
  "structured_data": {
    "profile": {
      "username": "skillsindia.in",
      "is_verified": true,
      "name": "Gaurav Kumar Bhushan",
      "title": "Real Estate Digital Marketer",
      "post_count": 82,
      "follower_count": "28K",
      "following_count": 600,
      "business_category": "Advertising Agency",
      "bio": "üèôÔ∏è Super Specialist Of Real Estate Marketing\nüèÜIcon of Asia Best Marketer for Real estate 2022\nPersuasion Expert\nAthletes Social media manager.",
      "external_links": [
        "youtube.com/@skillsindiain?si=kaUliSLCeqOxTuUc",
        "skillsindia.in"
      ]
    },
    "highlights": [
      "Product Shoots",
      "growth",
      "sec 5 - Gurgaon",
      "Peak Male Conten"
    ],
    "visible_reels": [
      {
        "title": "Hey PrabhuüòÇ",
        "views": "147K",
        "is_pinned": true
      },
      {
        "title": "This Is 100% Working Hack to get Viral On Instagram",
        "views": "248K",
        "is_pinned": true
      },
      {
        "title": "FROM ZERO TO ‚Çπ 5 LAKH IN COFFEE SALES?",
        "views": "565K",
        "is_pinned": true
      }
    ]
  },
  "profile_mentions": [
    "@skillsindiain"
  ],
  "additional_metadata": {
    "urls": [
      "youtube.com/@skillsindiain?si=kaUliSLCeqOxTuUc",
      "skillsindia.in"
    ],
    "locations": [
      "sec 5 - Gurgaon"
    ],
    "entities_mentioned": [
      "Dhruv Rathee",
      "‡§™‡•ç‡§∞‡§ß‡§æ‡§®‡§Æ‡§Ç‡§§‡•ç‡§∞‡•Ä ‡§Ü‡§µ‡§æ‡§∏ ‡§Ø‡•ã‡§ú‡§®‡§æ"
    ],
    "currency": "INR (‚Çπ)"
  }
}