{
  "filename": "Screenshot_20251012-171002 (1).webp",
  "tags": [
    "screenshot",
    "instagram",
    "social-media",
    "profile",
    "food",
    "cooking",
    "influencer",
    "indian",
    "recipes",
    "snacks",
    "content-creator",
    "hindi"
  ],
  "raw_text": "5:10\n154 KB/S VOLTE 5G 36\nsagarskitchenofficial\nSagar Kumar\n806 posts\n4.9M followers\n68 following\nसरफिरा बावर्ची\nSachhi Bata Rha Hai Bahut Tasty\nSagarsKitchen@echoxmedia.in\nwww.youtube.com/SagarsKitchen and 1 more\nSagar's Kitchen\nsagarskitchenofficial\nFollowed by nistachaturvedi_official and 29 others\nFollow\nMessage\nSubscribe\nTime Paas\nAchievement\nVikasKhannaSir\nAam Panna\nButter Chakli\n419K\nLite Chiwda Namkeen\n1.7M\nSoya Sticks Punjabi Tadka\n5.1M\nSagar's Kitchen\nCAPTURE MOMENT\nPawan Sahu\nNeetu Bisht\nCute.Shivani.03\nFilmy Suraj Actor\naman dancer real\nArtist Shintu Maurya\nSagar's Kitchen\nPriya Biswas\nPrashant Sharma Entertain...\nGreat Indian Asmr\nA VERY THANK YOU TO ALL OF YOU",
  "structured_data": {
    "profile": {
      "name": "Sagar Kumar",
      "username": "sagarskitchenofficial",
      "post_count": "806",
      "follower_count": "4.9M",
      "following_count": "68",
      "bio": "सरफिरा बावर्ची\nSachhi Bata Rha Hai Bahut Tasty",
      "email": "SagarsKitchen@echoxmedia.in",
      "external_links": [
        "www.youtube.com/SagarsKitchen",
        "Sagar's Kitchen (Facebook/Threads)",
        "sagarskitchenofficial (Threads/Instagram)"
      ],
      "highlights": [
        "Time Paas",
        "Achievement",
        "VikasKhannaSir"
      ]
    },
    "reels_feed": [
      {
        "title": "Butter Chakli",
        "views": "419K",
        "author": "Sagar's Kitchen"
      },
      {
        "title": "Lite Chiwda Namkeen",
        "views": "1.7M",
        "author": "Sagar's Kitchen"
      },
      {
        "title": "Soya Sticks Punjabi Tadka",
        "views": "5.1M",
        "author": "Sagar's Kitchen"
      }
    ]
  },
  "profile_mentions": [
    "nistachaturvedi_official",
    "sagarskitchenofficial",
    "Pawan Sahu",
    "Neetu Bisht",
    "Cute.Shivani.03",
    "Filmy Suraj Actor",
    "aman dancer real",
    "Artist Shintu Maurya",
    "Priya Biswas",
    "Prashant Sharma Entertain...",
    "Great Indian Asmr"
  ],
  "additional_metadata": {
    "email": "SagarsKitchen@echoxmedia.in",
    "urls": [
      "https://www.youtube.com/SagarsKitchen"
    ],
    "status_bar": {
      "time": "5:10",
      "network_speed": "154 KB/s",
      "network_type": "5G VoLTE",
      "battery_percentage": "36%"
    }
  }
}