{
  "filename": "Screenshot_20251102-203850 (1).webp",
  "tags": [
    "screenshot",
    "instagram",
    "profile",
    "animal",
    "rescue",
    "charity",
    "pakistan",
    "dog",
    "cat",
    "child",
    "donation",
    "fundraising",
    "reels",
    "socialmedia"
  ],
  "raw_text": "8:38\n41.0 KB/S VOLTE 5G 33\nhmf.animalrescue\nHajra Majeed\n418 posts 18.9K followers 725 following\nAnimal Rescue Service\nJust trying to make their life less difficult. üêæ\nWe can do it together if you want. ‚ù§Ô∏è\nJazzcash - 03084082121\n#faisalabad\ngofund.me/9318f153 and 1 more\nFollow Message Contact\nAhad üßê\nSeeyah ‚ù§Ô∏è\nJust watched\nKisi ki aik choti c muskurahat jeetna kisi bhi insaan ki sb se bari kamiyabi hai. ü§≤\nhajramajeedfoundation\n4.1M\n110K\nWhen tears are of happiness, they become the most beautiful tears in the world ü•∫üíñ‚ú®\nhajramajeedfoundation\nWhat Makes You Happy?\n24.4K\nRESCUE IS NOW CLOSED\nIf you can't help through donations, I sincerely apologize, but I cannot bring innocent souls to my shelter and watch them die helplessly.\nhajramajeedfoundation\nKisi ny bht khoob kaha hai k agar janweron k mazhab me inka shaitaan (INSAAN) hota.\nIf anyone wishes to give him a chance at a better life, please donate 5000 for his initial treatment.\nhajramajeedfoundation\nMer jaty hain to keeray khaty hain................",
  "structured_data": {
    "profile": {
      "username": "hmf.animalrescue",
      "display_name": "Hajra Majeed",
      "category": "Animal Rescue Service",
      "post_count": "418",
      "follower_count": "18.9K",
      "following_count": "725",
      "bio": "Just trying to make their life less difficult. üêæ We can do it together if you want. ‚ù§Ô∏è Jazzcash - 03084082121 #faisalabad",
      "external_links": [
        "gofund.me/9318f153"
      ],
      "story_highlights": [
        "Ahad üßê",
        "Seeyah ‚ù§Ô∏è"
      ]
    },
    "reels_feed": [
      {
        "view_count": "110K",
        "overlay_text": "When tears are of happiness, they become the most beautiful tears in the world ü•∫üíñ‚ú®",
        "watermark": "hajramajeedfoundation"
      },
      {
        "view_count": "4.1M",
        "overlay_text": "Just watched Kisi ki aik choti c muskurahat jeetna kisi bhi insaan ki sb se bari kamiyabi hai. ü§≤",
        "watermark": "hajramajeedfoundation"
      },
      {
        "view_count": "24.4K",
        "overlay_text": "What Makes You Happy?"
      },
      {
        "overlay_text": "RESCUE IS NOW CLOSED If you can't help through donations, I sincerely apologize, but I cannot bring innocent souls to my shelter and watch them die helplessly.",
        "watermark": "hajramajeedfoundation"
      },
      {
        "overlay_text": "Kisi ny bht khoob kaha hai k agar janweron k mazhab me inka shaitaan (INSAAN) hota. If anyone wishes to give him a chance at a better life, please donate 5000 for his initial treatment.",
        "watermark": "hajramajeedfoundation"
      },
      {
        "overlay_text": "Mer jaty hain to keeray khaty hain................",
        "watermark": "hajramajeedfoundation"
      }
    ]
  },
  "profile_mentions": [
    "hmf.animalrescue",
    "hajramajeedfoundation"
  ],
  "additional_metadata": {
    "phone_numbers": [
      "03084082121"
    ],
    "hashtags": [
      "#faisalabad"
    ],
    "urls": [
      "https://gofund.me/9318f153"
    ],
    "payment_methods": [
      "Jazzcash"
    ],
    "location": "Faisalabad"
  }
}