{
  "filename": "Screenshot_20251009-142541 (1).webp",
  "tags": [
    "advertisement",
    "numerology",
    "astrology",
    "business",
    "finance",
    "money",
    "laptop",
    "man",
    "services",
    "reports",
    "reselling"
  ],
  "raw_text": "MAAGNIFY\nASTRO NUMEROLOGY\nMAGNIFY\nNUMEROLOGY\nEARN THOUSANDS\nOF RUPEES DAILY\nSELLING NUMEROLOGY REPORTS\nWITHOUT ANY EFFORT\nEarn Thousands of Rupees ðŸ’µ daily selling Numerology\nreports ðŸ“• & Lucky SIMs with less efforts.\nI can provide you the below numerology reports for your\nclient ðŸ‘‡.\nYour name/email ID/phone number will be printed on the\nreport ðŸ“„.\n1. DOB Loshu Numerology Report with Remedies - 41\nPages\n2. Vedic Numerology Report with Remedies - 300 Pages\n3. Mobile Numerology Report with Remedies - 27 Pages\n4. Pythagorean Numerology Report with Remediesâ€”12\nPages\n5. Zenith & Obstacle Report - 6 Pages\n6. Pronology Report - 8 Pages\n7. Advanced Crystal Report - 3 Pages\n8. Lucky SIM all India Delivery\n9. Lucky Wristwatch, Swar Vigyan, Ramal Vigyan,\nProblem-based, specific remedies will be provided to\nyour clients.\n10. Will guide you on how to conduct a consultation with\nyour clients\n7083129651\nMaagnify Astro Numeroology\nðŸ“² 7083129651\nðŸ“§ magnifynumerology@gmail.com",
  "structured_data": {
    "business_name": "Maagnify Astro Numerology",
    "headline": "EARN THOUSANDS OF RUPEES DAILY SELLING NUMEROLOGY REPORTS WITHOUT ANY EFFORT",
    "value_proposition": "Allows individuals to sell numerology reports and Lucky SIMs with white-labeling (personal contact info on reports) and provides guidance on consultations.",
    "services_offered": [
      {
        "item": "DOB Loshu Numerology Report with Remedies",
        "details": "41 Pages"
      },
      {
        "item": "Vedic Numerology Report with Remedies",
        "details": "300 Pages"
      },
      {
        "item": "Mobile Numerology Report with Remedies",
        "details": "27 Pages"
      },
      {
        "item": "Pythagorean Numerology Report with Remedies",
        "details": "12 Pages"
      },
      {
        "item": "Zenith & Obstacle Report",
        "details": "6 Pages"
      },
      {
        "item": "Pronology Report",
        "details": "8 Pages"
      },
      {
        "item": "Advanced Crystal Report",
        "details": "3 Pages"
      },
      {
        "item": "Lucky SIM",
        "details": "All India Delivery"
      },
      {
        "item": "Other Services",
        "details": "Lucky Wristwatch, Swar Vigyan, Ramal Vigyan, Problem-based specific remedies"
      },
      {
        "item": "Consultation Support",
        "details": "Guidance on how to conduct a consultation"
      }
    ],
    "contact_information": {
      "phone": "7083129651",
      "email": "magnifynumerology@gmail.com"
    }
  },
  "profile_mentions": [],
  "additional_metadata": {
    "phone_numbers": [
      "7083129651"
    ],
    "emails": [
      "magnifynumerology@gmail.com"
    ],
    "currency": "Rupees"
  }
}