{
  "filename": "Screenshot_20251013-125031 (1).webp",
  "tags": [
    "advertisement",
    "digital marketing",
    "public relations",
    "service",
    "pricing",
    "biography",
    "wiki",
    "profile",
    "business",
    "media"
  ],
  "raw_text": "Sizi Tanınan Bir İsim\nHaline Getiriyoruz\nWikigenius, FoundersWiki ve Biyografya'da\ndijital kimliğinizi inşa ediyoruz.\nŞahsınızın, şirketinizin, derneğinizin veya\nprojenizin profesyonel profilini, güvenilir ve\nprestijli platformlarda oluşturuyoruz.\n• Şahsi 3'lü Paket\nWikigenius + FoundersWiki + Biyografya profili 10.000 TL\n• Şahsi + Şirket Profili\nKişisel + Kurumsal profil oluşturma 15.000 TL\n• İki Dilli Yayın (TR & EN)\nTürkçe ve İngilizce dilinde yayın 12.500 TL\n• 2 Ulusal Gazetede Haber Yayını +8.000 TL\n• Google Bilgi Paneli Entegrasyonu dahil 25.000 TL\n• Türkçe & İngilizce metin hazırlığı +2.000 TL\n• 40+ haber sitesinde PR yayını +6.000 TL\nEn Çok Tercih Edilen Paketler;\nŞahsi 3'lü Paket + Gazete Yayını: 17.500 TL\nŞahsi + Şirket Profili + Gazete Yayını: 18.000 TL\nŞahsi 3'lü + Bilgi Paneli: 25.000 TL\nFull PR Paketi (Tüm Hizmetler Dahil): 29.000 TL\nPyravis Medya Yapım & Akademi Yazılım Ltd. Şti.\n\"Dijital kimliğinizi profesyonel şekilde biz inşa ediyoruz.\"\nwww.pyravismedia.com\nwikigenius.org\nof the university youth magazine Kampüste Anonim.\nEnes Köseler\nBirth date April 22, 1996 (age 28)\nBirth place Kadıköy, İstanbul, Turkey\nNationality Turkish\nOccupation Businessman, Entrepreneur, PR Consultant, TV\nProducer, Urban Transformation Specialist\nWebsite eneskoseler.com\nEarly life and education\nCareer\nPublications\nprofil.patronsan.com\nPatronsan\nMeslek CEO\nCinsiyet Erkek\nDoğum tarihi Apr 22, 1996 (28 yaşında)\nDoğum Yeri Zonguldak\nEnes Köseler\nBaşarı Hikayesi\nEnes Köseler - İletişim Stratejisti, Kentsel Dönüşüm Danışmanı, PR Uzmanı, TV Yapımcısı ve Yazar 1996 yılında İstanbul Kadıköy'de dünyaya gelen Enes Köseler, medya, iletişim, pazarlama ve kentsel dönüşüm sektörlerinde uzmanlaşarak kariyerini çok yönlü bir başarı hikayesine dönüştürmüştür. Yakın Doğu Üniversitesi'nde Avrupa Birliği İlişkileri ve İşletme eğitimi alan Köseler, daha sonra Sakarya Üniversitesi Edebiyat Fakültesi'nde öğrenimini sürdürerek iletişim ve sosyal bilimler...\nŞirketi\nfounderswiki.org\nEnes Köseler\nEnes Köseler (born 22 April 1996) is a Turkish entrepreneur and communication professional. He works in the fields of public relations, media, production, urban transformation, and marketing. Köseler is known as the founder of Pyravis Media Production Academy Ltd., a company active in media, education and PR services.\nEnes Köseler\nBirth date April 22, 1996 (age 29)\nBirth place Kadıköy, Istanbul, Turkey\nNationality Turkish\nbiyografya.com\nBiyografya\nEnes Köseler\nYazar İletişimci Reklamcı Kent Bilimci\nDoğum 22 Nisan 1996 İstanbul\nEğitim Yakın Doğu Üniversitesi AB İlişkileri ve İşletme",
  "structured_data": {
    "service_provider": {
      "company_name": "Pyravis Medya Yapım & Akademi Yazılım Ltd. Şti.",
      "website": "www.pyravismedia.com",
      "slogan": "Dijital kimliğinizi profesyonel şekilde biz inşa ediyoruz."
    },
    "service_offerings": [
      {
        "service_name": "Şahsi 3’lü Paket (Wikigenius + FoundersWiki + Biyografya profili)",
        "price": "10.000 TL"
      },
      {
        "service_name": "Şahsi + Şirket Profili (Kişisel + Kurumsal profil oluşturma)",
        "price": "15.000 TL"
      },
      {
        "service_name": "İki Dilli Yayın (TR & EN) - Türkçe ve İngilizce dilinde yayın",
        "price": "12.500 TL"
      },
      {
        "service_name": "2 Ulusal Gazetede Haber Yayını",
        "price": "+8.000 TL"
      },
      {
        "service_name": "Google Bilgi Paneli Entegrasyonu dahil",
        "price": "25.000 TL"
      },
      {
        "service_name": "Türkçe & İngilizce metin hazırlığı",
        "price": "+2.000 TL"
      },
      {
        "service_name": "40+ haber sitesinde PR yayını",
        "price": "+6.000 TL"
      }
    ],
    "most_preferred_packages": [
      {
        "package_name": "Şahsi 3'lü Paket + Gazete Yayını",
        "price": "17.500 TL"
      },
      {
        "package_name": "Şahsi + Şirket Profili + Gazete Yayını",
        "price": "18.000 TL"
      },
      {
        "package_name": "Şahsi 3'lü + Bilgi Paneli",
        "price": "25.000 TL"
      },
      {
        "package_name": "Full PR Paketi (Tüm Hizmetler Dahil)",
        "price": "29.000 TL"
      }
    ],
    "sample_profile": {
      "name": "Enes Köseler",
      "birth_date": "April 22, 1996",
      "birth_place": [
        "Kadıköy, İstanbul, Turkey",
        "Zonguldak"
      ],
      "occupations": [
        "CEO",
        "Businessman",
        "Entrepreneur",
        "PR Consultant",
        "TV Producer",
        "Urban Transformation Specialist",
        "Writer",
        "Communication Professional",
        "Advertiser",
        "Urban Scientist"
      ],
      "education": [
        "Yakın Doğu Üniversitesi (AB İlişkileri ve İşletme)",
        "Sakarya Üniversitesi (Edebiyat Fakültesi)"
      ],
      "personal_website": "eneskoseler.com"
    }
  },
  "profile_mentions": [],
  "additional_metadata": {
    "urls": [
      "www.pyravismedia.com",
      "wikigenius.org",
      "profil.patronsan.com",
      "founderswiki.org",
      "biyografya.com",
      "eneskoseler.com"
    ],
    "currency": "TRY (Turkish Lira)",
    "languages": [
      "Turkish",
      "English"
    ],
    "important_dates": [
      "April 22, 1996"
    ]
  }
}