{
  "filename": "Screenshot_20251021-012502 (1).webp",
  "tags": [
    "screenshot",
    "instagram",
    "profile",
    "mobile",
    "finance",
    "business",
    "consultant",
    "money",
    "government",
    "loan",
    "india",
    "hindi"
  ],
  "raw_text": "1:25\n101 KB/S\nVoLTE\n5G\n27\nazadbusinessideas\nSANJAY MODI\n473 posts 207K followers 35 following\nBusiness Consultant\nYou give me 60 seconds every day and I will change your life.THE\nbest earing tips and tricks with Azad buisness\nfollow - azadbusiness\nlinktr.ee/Azadbusinessideas and 1 more\nazadbusinessideas\nAzad business\nFollowed by thenawazshaikh, dr.ravikgupta and\npatel.digital.advertising\nFollow Message Subscribe\nMillionaire Moment REEL HITS\nExclusive\nThank you Highlights\nINSTAGRAM\nHow?\n1.8M\nसरकार से LOAN 50 लाख\nREGISTER NOW\nBUSINESS GOVERNMENT SUPPORT\n1.1M\nभारत सरकार GOVERNMENT OF INDIA\n2.3M\nINDIA\n5 GOVERNMENT WEBSITE\nG Pay ₹49,829",
  "structured_data": {
    "profile": {
      "username": "azadbusinessideas",
      "display_name": "SANJAY MODI",
      "is_verified": true,
      "category": "Business Consultant",
      "posts_count": "473",
      "followers_count": "207K",
      "following_count": "35",
      "bio": "You give me 60 seconds every day and I will change your life.THE best earing tips and tricks with Azad buisness follow - azadbusiness",
      "external_links": [
        "linktr.ee/Azadbusinessideas"
      ],
      "other_profiles": [
        "azadbusinessideas (Threads)",
        "Azad business (YouTube)"
      ],
      "social_context": "Followed by thenawazshaikh, dr.ravikgupta and patel.digital.advertising"
    },
    "story_highlights": [
      {
        "label": "REEL HITS",
        "title": "Millionaire Moment"
      },
      {
        "label": "Exclusive",
        "title": "Sanjay Modi"
      },
      {
        "label": "Highlights",
        "title": "Thank you"
      },
      {
        "label": "INSTAGRAM",
        "title": "Instagram Logo"
      }
    ],
    "reels_feed": [
      {
        "title": "How?",
        "views": "1.8M"
      },
      {
        "title": "सरकार से LOAN 50 लाख",
        "views": "1.1M",
        "keywords": [
          "REGISTER NOW",
          "BUSINESS",
          "GOVERNMENT SUPPORT"
        ]
      },
      {
        "title": "भारत सरकार GOVERNMENT OF INDIA",
        "views": "2.3M"
      },
      {
        "title": "INDIA"
      },
      {
        "title": "5 GOVERNMENT WEBSITE"
      },
      {
        "title": "G Pay ₹49,829"
      }
    ]
  },
  "profile_mentions": [
    "@azadbusinessideas",
    "@azadbusiness",
    "@thenawazshaikh",
    "@dr.ravikgupta",
    "@patel.digital.advertising"
  ],
  "additional_metadata": {
    "urls": [
      "linktr.ee/Azadbusinessideas"
    ],
    "monetary_values": [
      "50 लाख",
      "₹49,829"
    ],
    "languages": [
      "English",
      "Hindi"
    ],
    "device_status": {
      "time": "1:25",
      "network": "5G",
      "battery": "27%"
    }
  }
}