{
  "filename": "Screenshot_20251031-182805 (1).webp",
  "tags": [
    "screenshot",
    "instagram",
    "social-media",
    "profile",
    "marketing",
    "ai",
    "viral",
    "content-creation",
    "business",
    "hooks",
    "storytelling",
    "niche",
    "reels"
  ],
  "raw_text": "6:28\nviralspot.ai\nViralspot Al\n11 posts\n2,344 followers\n9 following\nüéØ | Spot Viral Content in Seconds\nüìà | Create Hooks That Work\n‚è±Ô∏è | Save 1000+ Hours Researching\nComing soon ‚è≥\nviralspot.ai\nFollowed by emotionally.perfect\nFollow\nMessage\n50 Viral Hooks to Make Your Reels Go Viral\nLearn how to do STITCHING to go Viral\nThe old Instagram playbook doesn't work anymore\nHERE'S WHAT'S REPLACING IT IN 2025...\n30 Storytelling Phrases That Instantly Captivate Your Audience\nYour Niche ‚â† Your Product\nLET'S CLEAR UP THE CONFUSION\nYou don't need fancy edits to go Viral\n30 Quick Hooks That Stop the Scroll Instantly\nPost Your Videos Again and Go Viral\nSuccess\nPOSTING THREE TIMES A WEEK\nSuccess",
  "structured_data": {
    "profile": {
      "username": "viralspot.ai",
      "display_name": "Viralspot Al",
      "is_verified": true,
      "post_count": 11,
      "follower_count": "2,344",
      "following_count": 9,
      "bio": "üéØ | Spot Viral Content in Seconds\nüìà | Create Hooks That Work\n‚è±Ô∏è | Save 1000+ Hours Researching\nComing soon ‚è≥",
      "website": "viralspot.ai",
      "followed_by": "emotionally.perfect"
    },
    "grid_content": [
      {
        "type": "carousel",
        "title": "50 Viral Hooks to Make Your Reels Go Viral"
      },
      {
        "type": "video",
        "title": "Learn how to do STITCHING to go Viral"
      },
      {
        "type": "carousel",
        "title": "The old Instagram playbook doesn't work anymore",
        "subtitle": "HERE'S WHAT'S REPLACING IT IN 2025..."
      },
      {
        "type": "carousel",
        "title": "30 Storytelling Phrases That Instantly Captivate Your Audience"
      },
      {
        "type": "carousel",
        "title": "Your Niche ‚â† Your Product",
        "subtitle": "LET'S CLEAR UP THE CONFUSION"
      },
      {
        "type": "video",
        "title": "You don't need fancy edits to go Viral"
      },
      {
        "type": "carousel",
        "title": "30 Quick Hooks That Stop the Scroll Instantly"
      },
      {
        "type": "video",
        "title": "Post Your Videos Again and Go Viral"
      },
      {
        "type": "video",
        "title": "POSTING THREE TIMES A WEEK",
        "visual_elements": "Scale weighing 'Success'"
      }
    ]
  },
  "profile_mentions": [
    "@viralspot.ai",
    "@emotionally.perfect"
  ],
  "additional_metadata": {
    "url": "viralspot.ai",
    "status_bar_info": {
      "time": "6:28",
      "network": "5G, VolTE",
      "battery": "35%"
    },
    "theme": "dark mode"
  }
}