{
  "filename": "Screenshot_20251030-024526 (1).webp",
  "tags": [
    "screenshot",
    "instagram",
    "reel",
    "poetry",
    "activism",
    "biography",
    "history",
    "india",
    "jnu",
    "student",
    "protest",
    "documentary",
    "hindi",
    "social",
    "political"
  ],
  "raw_text": "2:45\n* 36.1 KB/S VOLTE 5G 94\nReels\nFriends\nmp4vaultindia\nRamashankar Yadav (1957 - 2015), also known as Vidrohi, was an Indian poet and social activist who went to Jawaharlal Nehru University (JNU) as a student but continued to live on or around its campus well beyond his student life.\nwhich neither rewards\nnor punches the poet\nAlways present during student protests, reciting his revolutionary poetry at such occasions, and otherwise at Ganga Dhaba, was a common sight. He died participating in a student protest in Delhi. He was a progressive poet with reformative spirit. He tried to sensitise the society at large against religious superstition, gender discrimination and economic inequality in society through his poems. He was vocal against state repression, persecution of the marginalised section of society and crackdown on voice of dissenting opinion.\n[ JNU, Poetry, Art, Revolution, Student, Different, Kavita, Hindi, Crime Against Women ]\nVideo: Main Tumhara Kavi Hoon (2011)\nDirected by Nitin K. Pamnani & Imran Khan\nLiked by wordaaddict_ and 60,667 others\n60.6K\n215\n2,005\n14.4K",
  "structured_data": {
    "platform": "Instagram",
    "content_type": "Reel",
    "author": {
      "username": "mp4vaultindia"
    },
    "post_metrics": {
      "likes_display": "60.6K",
      "exact_likes": "60,667 others",
      "comments": "215",
      "shares": "14.4K",
      "reposts": "2,005"
    },
    "caption_details": {
      "subject": "Ramashankar Yadav (Vidrohi)",
      "subject_lifespan": "1957 - 2015",
      "description": "Biography of an Indian poet and social activist known for his work at JNU and revolutionary poetry.",
      "keywords": [
        "JNU",
        "Poetry",
        "Art",
        "Revolution",
        "Student",
        "Different",
        "Kavita",
        "Hindi",
        "Crime Against Women"
      ],
      "source_video": "Main Tumhara Kavi Hoon (2011)",
      "directors": [
        "Nitin K. Pamnani",
        "Imran Khan"
      ]
    },
    "device_status": {
      "time": "2:45",
      "connection": "5G",
      "battery": "94%"
    }
  },
  "profile_mentions": [
    "wordaaddict_",
    "mp4vaultindia"
  ],
  "additional_metadata": {
    "dates_mentioned": [
      "1957",
      "2015",
      "2011"
    ],
    "locations_mentioned": [
      "Jawaharlal Nehru University (JNU)",
      "Delhi",
      "Ganga Dhaba"
    ]
  }
}