{
  "filename": "Screenshot_20251016-181441 (1).webp",
  "tags": [
    "screenshot",
    "graduation",
    "convocation",
    "SRM",
    "certificate",
    "medal",
    "achievement",
    "education",
    "award",
    "rank",
    "university",
    "success",
    "manikandan"
  ],
  "raw_text": "6:14\n1.32 MB/S\nVoLTE 5G\n33\n‚ÄúCongratulations, Mr. Manikandan! Witnessing the\nmoment you received your gold medal was truly\ndelightful. This is just the beginning‚Äîthere is much\nmore greatness ahead. Wishing you all the best!‚Äù\nSRM\nINSTITUTE OF SCIENCE AND TECHNOLOGY\n(DEEMED TO BE UNIVERSITY UNDER SECTION 3 OF THE UGC ACT, 1956)\nRank Certificate\nThis is to certify that MANIKANDAN K N\nhas secured the FIRST RANK\nin the M.Sc. VISUAL COMMUNICATION\nprogramme among the candidates who graduated in\nAPRIL-2023 on the basis of performance in\nall the examinations held during 2021 - 2023\nThank you so much Dr salai ü•πüôèü´Ç\nCONVOCATION-2023\n1st\nRANK\nMANIKANDAN K N\nM.Sc.\nVisual Communication",
  "structured_data": {
    "document_details": {
      "institution": "SRM Institute of Science and Technology",
      "certificate_type": "Rank Certificate",
      "recipient_name": "MANIKANDAN K N",
      "achievement": "FIRST RANK / 1st RANK Gold Medal",
      "degree_program": "M.Sc. VISUAL COMMUNICATION",
      "graduation_month_year": "APRIL-2023",
      "academic_period": "2021 - 2023",
      "convocation_year": "2023"
    },
    "social_media_content": {
      "congratulatory_message": "Congratulations, Mr. Manikandan! Witnessing the moment you received your gold medal was truly delightful. This is just the beginning‚Äîthere is much more greatness ahead. Wishing you all the best!",
      "response_message": "Thank you so much Dr salai ü•πüôèü´Ç"
    }
  },
  "profile_mentions": [],
  "additional_metadata": {
    "phone_ui_info": {
      "time": "6:14",
      "data_speed": "1.32 MB/S",
      "network_type": "5G, VoLTE",
      "battery_level": "33%"
    },
    "mentioned_individuals": [
      "Manikandan",
      "Dr salai"
    ]
  }
}