{
  "filename": "Screenshot_20251028-093048 (1).webp",
  "tags": [
    "screenshot",
    "instagram",
    "farming",
    "agriculture",
    "regenerative",
    "art",
    "welding",
    "food",
    "gardening",
    "DIY",
    "socialmedia",
    "profile"
  ],
  "raw_text": "9:30\n4.88 KB/S\nVoLTE\n4G\n28\nsonglandfarms\nSongland Farms\n389 posts\n68.9K followers\n405 following\nSmall scale, regenerative, no-till farm.\nğŸ‡¬ğŸ‡· Food Truck @kastrotx coming soon\nğŸ¸ @dylan.kongos @amberdenison.art\nğŸ¥ @kongosmusic ğŸ§µ @shelleykongos\nsonglandfarms.square.site/shop/amber-art/NNSBQC5BACB...\nsonglandfarms\nFollow\nMessage\nShop\nDay 5 of posting all the cool shit my wife does until her art finds an audience\n1.6M\n4 years ago we left the city and started a garden for the family\n467K\nDay 1 of posting all the cool shit my wife does until her art finds an audience\n3.9M\nWashing greens with a jacuzzi bubbler ğŸ˜‚\n7,185\nWe built a huge salad spinner out of a washing machine ğŸ˜‚\n17.9K\nPlanting 1000 seedlings in minutes with no tractor, no gas, no powered tools ğŸ› ï¸\nJust watched\n677K",
  "structured_data": {
    "profile": {
      "name": "Songland Farms",
      "username": "songlandfarms",
      "is_verified": true,
      "posts_count": "389",
      "followers_count": "68.9K",
      "following_count": "405",
      "bio": "Small scale, regenerative, no-till farm.\nğŸ‡¬ğŸ‡· Food Truck @kastrotx coming soon\nğŸ¸ @dylan.kongos @amberdenison.art\nğŸ¥ @kongosmusic ğŸ§µ @shelleykongos",
      "external_links": [
        "songlandfarms.square.site/shop/amber-art/NNSBQC5BACB...",
        "songlandfarms (Threads)"
      ]
    },
    "reels_feed": [
      {
        "text": "Day 5 of posting all the cool shit my wife does until her art finds an audience",
        "view_count": "1.6M",
        "is_pinned": true
      },
      {
        "text": "4 years ago we left the city and started a garden for the family",
        "view_count": "467K",
        "is_pinned": true
      },
      {
        "text": "Day 1 of posting all the cool shit my wife does until her art finds an audience",
        "view_count": "3.9M",
        "is_pinned": true
      },
      {
        "text": "Washing greens with a jacuzzi bubbler ğŸ˜‚",
        "view_count": "7,185"
      },
      {
        "text": "We built a huge salad spinner out of a washing machine ğŸ˜‚",
        "view_count": "17.9K"
      },
      {
        "text": "Planting 1000 seedlings in minutes with no tractor, no gas, no powered tools ğŸ› ï¸",
        "status": "Just watched",
        "view_count": "677K"
      }
    ]
  },
  "profile_mentions": [
    "@kastrotx",
    "@dylan.kongos",
    "@amberdenison.art",
    "@kongosmusic",
    "@shelleykongos"
  ],
  "additional_metadata": {
    "urls": [
      "https://songlandfarms.square.site/shop/amber-art/NNSBQC5BACB..."
    ],
    "hashtags": [],
    "emojis": [
      "ğŸ‡¬ğŸ‡·",
      "ğŸ¸",
      "ğŸ¥",
      "ğŸ§µ",
      "ğŸ˜‚",
      "ğŸ› ï¸"
    ]
  }
}