{
  "filename": "Screenshot_20251109-114010 (1).webp",
  "tags": [
    "screenshot",
    "instagram",
    "environment",
    "pollution",
    "water",
    "cleanup",
    "science",
    "biology",
    "nematodes",
    "India",
    "sustainability",
    "research",
    "microscopic",
    "technology",
    "Ahmedabad",
    "Gujarat"
  ],
  "raw_text": "11:40\n270 KB/s VoLTE 5G 75\nSource: YT/Travel for Tourism/Scroll.in\nthe better india\nthat can clean even the\nMeet the tiniest cleanup crew on the planet, Acrobeloides Maximus, a.k.a. the nematodes.\nInvisible to the eye, but mighty in mission - these microscopic worms can turn filthy lakes crystal clean in just one week. ğŸ’§\nIn Ahmedabad, a Gujarat University researcher bred these nematodes inside jelly-like capsules and dropped them into Kankaria and Virat Sarovar â€” two of the city's most polluted lakes.\nThe result?\nâœ¨ Water pollution levels dropped dramatically.\nğŸŒ¿ Ecosystems revived naturally.\nğŸ’° Low-cost, eco-friendly, and 100% safe for aquatic life.\nSometimes, innovation doesn't roar â€” it wriggles quietly beneath the surface.\nBecause sustainability isn't always about grand inventions; it's about small actions that make big impact.\nWould you want these wonder worms cleaning your city's lakes next? ğŸŒ\nCredit: The Better India & Sunita Chauhan (Gujarat University)",
  "structured_data": {
    "post_content": {
      "headline": "Meet the tiniest cleanup crew on the planet, Acrobeloides Maximus, a.k.a. the nematodes.",
      "description": "Invisible to the eye, but mighty in mission - these microscopic worms can turn filthy lakes crystal clean in just one week.",
      "case_study": {
        "location": "Ahmedabad",
        "institution": "Gujarat University",
        "researcher": "Sunita Chauhan",
        "test_sites": [
          "Kankaria Lake",
          "Virat Sarovar"
        ],
        "method": "Bred nematodes inside jelly-like capsules and dropped them into polluted lakes."
      },
      "results": [
        "Water pollution levels dropped dramatically.",
        "Ecosystems revived naturally.",
        "Low-cost, eco-friendly, and 100% safe for aquatic life."
      ],
      "philosophical_note": "Sometimes, innovation doesn't roar â€” it wriggles quietly beneath the surface. Because sustainability isn't always about grand inventions; it's about small actions that make big impact."
    },
    "credits": {
      "publisher": "The Better India",
      "researcher": "Sunita Chauhan",
      "institution": "Gujarat University",
      "visual_sources": [
        "YT/Travel for Tourism",
        "Scroll.in"
      ]
    }
  },
  "profile_mentions": [],
  "additional_metadata": {
    "urls": [
      "Scroll.in"
    ],
    "time": "11:40",
    "battery_percentage": "75%",
    "network_info": "5G, VoLTE",
    "emojis": [
      "ğŸ’§",
      "âœ¨",
      "ğŸŒ¿",
      "ğŸ’°",
      "ğŸŒ"
    ]
  }
}