{
  "filename": "Screenshot_20251011-102259 (1).webp",
  "tags": [
    "screenshot",
    "LinkedIn",
    "profile",
    "professional",
    "psychology",
    "hypnotherapy",
    "counseling",
    "therapy",
    "healing",
    "biography",
    "Singapore"
  ],
  "raw_text": "Jefferin Sequeira Â· 3rd\nFounder Director, Centre Space Therapy & Healing\nLondon College of Clinical Hypnosis\nSingapore\n52 connections\nMessage\nFollow\n...\nAbout\nFounder Director of Centre Space, Singapore, is a Psychologist,\nPersonal Relationship Counselor & Clinical Hypnotherapist - affiliate,\nBritish Society of Clinical Hypnotherapists, (Membership No 13806).\nProfessional Certification includes: a Masters in Industrial\nPsychology, Post-Graduate Diploma in Human Resources\nManagement, Diploma in Counseling and Diploma in Clinical\nHypnotherapy accredited to the British Society of Clinical\nHypnotherapists.\nHaving lived in India, the Middle East, Australia, Europe and\nSingapore with professional working experience spanning 15 years,\nnumerous cross cultural challenges and experiences became the\npivot for her Self-Transformation wherein she sought answers to the\ndeepest issues of 'Meaning' and 'Purpose' of 'Life'. Wherever she\nwent, Jefferin spontaneously re-invented herself and excelled in\nlooking at adversity as an opportunity for personal growth and\nfreedom, maintaining her passion and zest to Thrive by Living &\nLearning,\noffer therapeutic healing by integrating counseling with\nhypnotherapy, synchronizing the mind and body by releasing past\nemotional baggage, traumas, afflictions, conflicts and repressed\nenergies thereby effecting healing of your subconscious mind. Once\nhealing takes place you can unleash and harness the amazing wealth\nwithin your subconscious mind and get it to work for you efficiently\nand effectively. By tapping into the superior capacities and\nactualizing your full potential you can move forward from a life of\nself-imposed limitation to a life of ABUNDANCE",
  "structured_data": {
    "profile": {
      "name": "Jefferin Sequeira",
      "connection_degree": "3rd",
      "headline": "Founder Director, Centre Space Therapy & Healing",
      "education_summary": "London College of Clinical Hypnosis",
      "location": "Singapore",
      "connection_count": "52",
      "about_section": {
        "summary": "Founder Director of Centre Space, Singapore. Psychologist, Personal Relationship Counselor & Clinical Hypnotherapist with 15 years of international experience.",
        "professional_titles": [
          "Founder Director",
          "Psychologist",
          "Personal Relationship Counselor",
          "Clinical Hypnotherapist"
        ],
        "affiliations": [
          {
            "organization": "British Society of Clinical Hypnotherapists",
            "membership_number": "13806"
          }
        ],
        "certifications": [
          "Masters in Industrial Psychology",
          "Post-Graduate Diploma in Human Resources Management",
          "Diploma in Counseling",
          "Diploma in Clinical Hypnotherapy (BSCH accredited)"
        ],
        "work_experience_years": 15,
        "regions_of_experience": [
          "India",
          "Middle East",
          "Australia",
          "Europe",
          "Singapore"
        ],
        "therapeutic_approach": "Integrating counseling with hypnotherapy to synchronize mind and body and release emotional baggage."
      }
    }
  },
  "profile_mentions": [],
  "additional_metadata": {
    "membership_no": "13806",
    "organizations_mentioned": [
      "Centre Space Therapy & Healing",
      "London College of Clinical Hypnosis",
      "British Society of Clinical Hypnotherapists"
    ]
  }
}