{
  "filename": "Screenshot_20251113-050807 (1).webp",
  "tags": [
    "screenshot",
    "instagram",
    "profile",
    "social-media",
    "content-strategy",
    "marketing",
    "education",
    "influencer",
    "podcast",
    "kolkata",
    "india",
    "business",
    "mobile-app"
  ],
  "raw_text": "5:08\n141 KB/S VoLTE 5G 49\nkadakcontent\nPritika Loonia\n272 posts\n990K followers\n58 following\nContent Strategist üìç Kolkata\n1 Million in 5 months here- @pritika.loonia\nPodcast Host @sageupwithpritika\nkadakcontent@gmail.com\nlinktr.ee/kadakcontent\nCoach Contento AI\nFollowed by camo_crest07, millionaire_upkar and 61 others\nFollow\nMessage\n100k in 100 day\nMilestones\nScammers!\nResults\n100K FOLLOWERS IN 100 DAYS PART 1\n1.8M\n100K FOLLOWERS IN 100 DAYS PART 3\n583K\n#ASHTAG SE KOI ZYADA FARAK NAHI PADNE\n124K\nSILLY MISTAKES JO CREATORS KRTE HAI PART 1\nThere are scammers everywhere, do not fall into this trap! My course is available only on my website\nne apke video's ba... na...but ... krke instagram pr ek log ko mene paise de diye...wo na course de the aur na hi fee refund kar rhe",
  "structured_data": {
    "profile": {
      "username": "kadakcontent",
      "name": "Pritika Loonia",
      "is_verified": true,
      "posts": "272",
      "followers": "990K",
      "following": "58",
      "bio": "Content Strategist üìç Kolkata\n1 Million in 5 months here- @pritika.loonia\nPodcast Host @sageupwithpritika\nkadakcontent@gmail.com\nlinktr.ee/kadakcontent\nCoach Contento AI",
      "common_followers": [
        "camo_crest07",
        "millionaire_upkar"
      ]
    },
    "story_highlights": [
      "100k in 100 day",
      "Milestones",
      "Scammers!",
      "Results"
    ],
    "posts_preview": [
      {
        "title": "100K FOLLOWERS IN 100 DAYS PART 1",
        "views": "1.8M",
        "is_pinned": true
      },
      {
        "title": "100K FOLLOWERS IN 100 DAYS PART 3",
        "views": "583K",
        "is_pinned": true
      },
      {
        "title": "#ASHTAG SE KOI ZYADA FARAK NAHI PADNE",
        "views": "124K",
        "is_pinned": false
      },
      {
        "title": "SILLY MISTAKES JO CREATORS KRTE HAI PART 1",
        "views": null,
        "is_pinned": false
      }
    ]
  },
  "profile_mentions": [
    "@pritika.loonia",
    "@sageupwithpritika",
    "camo_crest07",
    "millionaire_upkar"
  ],
  "additional_metadata": {
    "email": "kadakcontent@gmail.com",
    "url": "https://linktr.ee/kadakcontent",
    "hashtags": [
      "#ASHTAG"
    ],
    "location": "Kolkata",
    "device_info": {
      "time": "5:08",
      "battery": "49%",
      "network_type": "5G",
      "signal_strength": "VoLTE"
    }
  }
}